[{"datasetid": "hebergements-classes", "recordid": "90e0261d1a384d5ad675dcdec5bf5d22676a5881", "fields": {"commune": "SAINT-CAST-LE-GUILDO", "classement": "2 \u00e9toiles", "categorie": "-", "nom_epci": "CA Dinan Agglom\u00e9ration", "date_de_publication_de_l_etablissement": "2012-10-16", "nom_reg": "BRETAGNE", "courriel": "germain@hotel-de-lesperance.com", "adresse": "6 rue jacques cartier", "nom_commercial": "H\u00d4TEL DE L'ESP\u00c9RANCE", "date_de_classement": "2012-10-16", "telephone": "0296418113", "capacite_daccueil_personnes": 13, "typologie_etablissement": "H\u00d4TEL", "nombre_de_chambres": 6, "code_postal": "22380", "nom_dep": "COTES-D'ARMOR", "coordonnees": [48.633193, -2.256972], "site_internet": "www.hotel-de-lesperance.com"}, "geometry": {"type": "Point", "coordinates": [-2.256972, 48.633193]}, "record_timestamp": "2020-07-08T10:30:41.649+02:00"},{"datasetid": "hebergements-classes", "recordid": "cb3c89b94450fcce612f2ee2cc4e37ff4e1c9a05", "fields": {"commune": "DINAN", "classement": "2 \u00e9toiles", "categorie": "-", "nom_epci": "CA Dinan Agglom\u00e9ration", "date_de_publication_de_l_etablissement": "2012-10-19", "nom_reg": "BRETAGNE", "courriel": "hotelrestau.lamarmite@orange.fr", "adresse": "91 rue de brest", "nom_commercial": "H\u00d4TEL RESTAURANT LA MARMITE", "date_de_classement": "2012-10-19", "telephone": "0296390442", "capacite_daccueil_personnes": 13, "typologie_etablissement": "H\u00d4TEL", "nombre_de_chambres": 5, "code_postal": "22100", "nom_dep": "COTES-D'ARMOR", "coordonnees": [48.452172, -2.060186], "site_internet": "lamarmitedinan.fr"}, "geometry": {"type": "Point", "coordinates": [-2.060186, 48.452172]}, "record_timestamp": "2020-07-08T10:30:41.649+02:00"},{"datasetid": "hebergements-classes", "recordid": "f554f8b6df9de3cb5570e095157e2c32a9767f35", "fields": {"commune": "BELLE-ISLE-EN-TERRE", "classement": "2 \u00e9toiles", "categorie": "-", "nom_epci": "CA Guingamp-Paimpol Armor-Argoat Agglom\u00e9ration", "date_de_publication_de_l_etablissement": "2013-07-18", "nom_reg": "BRETAGNE", "courriel": "lerelaisdelargoat@orange.fr", "adresse": "9 rue du guic", "nom_commercial": "LE RELAIS DE L'ARGOAT", "date_de_classement": "2013-07-18", "telephone": "0296430034", "capacite_daccueil_personnes": 18, "typologie_etablissement": "H\u00d4TEL", "nombre_de_chambres": 8, "code_postal": "22810", "nom_dep": "COTES-D'ARMOR", "coordonnees": [48.543869, -3.397672], "site_internet": "www.lerelaisdelargoat.fr"}, "geometry": {"type": "Point", "coordinates": [-3.397672, 48.543869]}, "record_timestamp": "2020-07-08T10:30:41.649+02:00"},{"datasetid": "hebergements-classes", "recordid": "36120e2ca72e7f9f421c3dbc0057f074741b6671", "fields": {"commune": "LANNION", "classement": "3 \u00e9toiles", "categorie": "-", "nom_epci": "CA Lannion-Tr\u00e9gor Communaut\u00e9", "date_de_publication_de_l_etablissement": "2017-04-01", "nom_reg": "BRETAGNE", "courriel": "h3401@accor.com", "adresse": "30 AVENUE DU G\u00c9N\u00c9RAL DE GAULLE", "nom_commercial": "H\u00d4TEL IBIS LANNION C\u00d4TE DE GRANIT ROSE", "date_de_classement": "2017-04-01", "telephone": "0296370367", "capacite_daccueil_personnes": 158, "typologie_etablissement": "H\u00d4TEL", "nombre_de_chambres": 70, "code_postal": "22300", "nom_dep": "COTES-D'ARMOR", "coordonnees": [48.728292, -3.460552], "site_internet": "http://www.accorhotels.com/fr/hotel-3401-ibis-lannion-cote-de-granit-rose/index.shtml"}, "geometry": {"type": "Point", "coordinates": [-3.460552, 48.728292]}, "record_timestamp": "2020-07-08T10:30:41.649+02:00"},{"datasetid": "hebergements-classes", "recordid": "e2fcc4a7cf5be1fdc0522047a8e4e89f16c55ec4", "fields": {"commune": "TR\u00c9BEURDEN", "classement": "1 \u00e9toile", "categorie": "-", "nom_epci": "CA Lannion-Tr\u00e9gor Communaut\u00e9", "date_de_publication_de_l_etablissement": "2014-07-31", "nom_reg": "BRETAGNE", "courriel": "lecumedemer@orange.fr", "adresse": "16 CORNICHE GAOS TREIZ", "nom_commercial": "H\u00d4TEL L'\u00c9CUME DE MER", "date_de_classement": "2014-07-31", "telephone": "0296235060", "capacite_daccueil_personnes": 48, "typologie_etablissement": "H\u00d4TEL", "nombre_de_chambres": 24, "code_postal": "22560", "nom_dep": "COTES-D'ARMOR", "coordonnees": [48.778555, -3.579367], "site_internet": "http://lecumedemer.blogspot.fr/"}, "geometry": {"type": "Point", "coordinates": [-3.579367, 48.778555]}, "record_timestamp": "2020-07-08T10:30:41.649+02:00"},{"datasetid": "hebergements-classes", "recordid": "5f2bed44bfa93628162d0fa9004810e1540a24f3", "fields": {"commune": "PLURIEN", "classement": "2 \u00e9toiles", "categorie": "-", "nom_epci": "CA Lamballe Terre et Mer", "date_de_publication_de_l_etablissement": "2014-08-13", "nom_reg": "BRETAGNE", "courriel": "contact@hotel-le-bon-cap.com", "adresse": "10 rue de Montangu\u00e9", "nom_commercial": "H\u00d4TEL LE BON CAP", "date_de_classement": "2014-08-13", "telephone": "02 96 52 40 33", "capacite_daccueil_personnes": 26, "typologie_etablissement": "H\u00d4TEL", "nombre_de_chambres": 11, "code_postal": "22240", "nom_dep": "COTES-D'ARMOR", "coordonnees": [48.625996, -2.405326], "site_internet": "http://www.hotel-le-bon-cap.com/"}, "geometry": {"type": "Point", "coordinates": [-2.405326, 48.625996]}, "record_timestamp": "2020-07-08T10:30:41.649+02:00"},{"datasetid": "hebergements-classes", "recordid": "31ac54dcb26670e453332eb41d90b794f8727d75", "fields": {"commune": "YFFINIAC", "classement": "2 \u00e9toiles", "categorie": "-", "nom_epci": "CA Saint-Brieuc Armor Agglom\u00e9ration", "date_de_publication_de_l_etablissement": "2017-05-01", "nom_reg": "BRETAGNE", "courriel": "H5686-RE@ACCOR.COM", "adresse": "36 RUE JULIEN QUINTIN", "nom_commercial": "H\u00d4TEL IBIS BUDGET SAINT BRIEUC YFFINIAC", "date_de_classement": "2017-05-01", "telephone": "0892684027", "capacite_daccueil_personnes": 90, "typologie_etablissement": "H\u00d4TEL", "nombre_de_chambres": 30, "code_postal": "22120", "nom_dep": "COTES-D'ARMOR", "coordonnees": [48.480415, -2.66414], "site_internet": "http://www.accorhotels.com/fr/hotel-5686-ibis-budget-saint-brieuc-yffiniac/index.shtml"}, "geometry": {"type": "Point", "coordinates": [-2.66414, 48.480415]}, "record_timestamp": "2020-07-08T10:30:41.649+02:00"},{"datasetid": "hebergements-classes", "recordid": "9f3c0af46522fe778210221a1febfc17a8c16f48", "fields": {"commune": "PLANGUENOUAL", "classement": "3 \u00e9toiles", "categorie": "-", "nom_epci": "CA Lamballe Terre et Mer", "date_de_publication_de_l_etablissement": "2013-02-08", "nom_reg": "BRETAGNE", "courriel": "chateau-du-val@wanadoo.fr", "adresse": "le val", "nom_commercial": "CH\u00c2TEAU DU VAL", "date_de_classement": "2013-02-08", "telephone": "0296327540", "capacite_daccueil_personnes": 81, "typologie_etablissement": "H\u00d4TEL", "nombre_de_chambres": 36, "code_postal": "22400", "nom_dep": "COTES-D'ARMOR", "coordonnees": [48.545546, -2.596526], "site_internet": "www.chateau-du-val.com"}, "geometry": {"type": "Point", "coordinates": [-2.596526, 48.545546]}, "record_timestamp": "2020-07-08T10:30:41.649+02:00"},{"datasetid": "hebergements-classes", "recordid": "b25741338aee7a43b38f24234a15eab8dcb2c089", "fields": {"commune": "PL\u00c9RIN", "classement": "4 \u00e9toiles", "categorie": "-", "nom_epci": "CA Saint-Brieuc Armor Agglom\u00e9ration", "date_de_publication_de_l_etablissement": "2016-02-06", "nom_reg": "BRETAGNE", "courriel": "plerin@brithotel.fr", "adresse": "ZAC DE L\u2019ARRIV\u00c9E 4 RUE FRAN\u00c7OIS JACOB", "nom_commercial": "BRIT H\u00d4TEL SAINT BRIEUC PL\u00c9RIN", "date_de_classement": "2016-02-06", "telephone": "0296788003", "capacite_daccueil_personnes": 146, "typologie_etablissement": "H\u00d4TEL", "nombre_de_chambres": 65, "code_postal": "22190", "nom_dep": "COTES-D'ARMOR", "coordonnees": [48.547899, -2.790204], "site_internet": "http://st-brieuc-plerin.brit-hotel.fr/"}, "geometry": {"type": "Point", "coordinates": [-2.790204, 48.547899]}, "record_timestamp": "2020-07-08T10:30:41.649+02:00"},{"datasetid": "hebergements-classes", "recordid": "cbc912c99f1b41589452b23f60b092f29141611d", "fields": {"commune": "PAIMPOL", "classement": "3 \u00e9toiles", "categorie": "-", "nom_epci": "CA Guingamp-Paimpol Armor-Argoat Agglom\u00e9ration", "date_de_publication_de_l_etablissement": "2017-05-19", "nom_reg": "BRETAGNE", "courriel": "info@paimpol-eurotel.com", "adresse": "2 chemin de Kergroas", "nom_commercial": "H\u00d4TEL EUROTEL LE GRAND BLEU", "date_de_classement": "2017-05-19", "telephone": "0296208185", "capacite_daccueil_personnes": 60, "typologie_etablissement": "H\u00d4TEL", "nombre_de_chambres": 30, "code_postal": "22500", "nom_dep": "COTES-D'ARMOR", "coordonnees": [48.76753, -3.04074], "site_internet": "http://www.paimpol-eurotel.com"}, "geometry": {"type": "Point", "coordinates": [-3.04074, 48.76753]}, "record_timestamp": "2020-07-08T10:30:41.649+02:00"},{"datasetid": "hebergements-classes", "recordid": "4932a6279c9346c91c31cc40856032ba951ddd1d", "fields": {"commune": "TADEN", "classement": "3 \u00e9toiles", "categorie": "-", "nom_epci": "CA Dinan Agglom\u00e9ration", "date_de_publication_de_l_etablissement": "2016-11-24", "nom_reg": "BRETAGNE", "courriel": "hotel.alleux@wanadoo.fr", "adresse": "la billardais, route de Ploubalay", "nom_commercial": "H\u00d4TEL DES ALLEUX", "date_de_classement": "2016-11-24", "telephone": "0296851610", "capacite_daccueil_personnes": 102, "typologie_etablissement": "H\u00d4TEL", "nombre_de_chambres": 51, "code_postal": "22100", "nom_dep": "COTES-D'ARMOR", "coordonnees": [48.480193, -2.027548], "site_internet": "http://www.hotel-les-alleux-dinan.com/"}, "geometry": {"type": "Point", "coordinates": [-2.027548, 48.480193]}, "record_timestamp": "2020-07-08T10:30:41.649+02:00"},{"datasetid": "hebergements-classes", "recordid": "2b62ebfd350207d2e01cf571dab66f2751ee07c5", "fields": {"commune": "PL\u00c9VENON", "classement": "2 \u00e9toiles", "categorie": "-", "nom_epci": "CA Dinan Agglom\u00e9ration", "date_de_publication_de_l_etablissement": "2014-07-31", "nom_reg": "BRETAGNE", "courriel": "hotel.le-trecelin@wanadoo.fr", "adresse": "16 rue du petit tr\u00e9celin", "nom_commercial": "H\u00d4TEL LE TR\u00c9CELIN", "date_de_classement": "2014-07-31", "telephone": "0296414682", "capacite_daccueil_personnes": 50, "typologie_etablissement": "H\u00d4TEL", "nombre_de_chambres": 22, "code_postal": "22240", "nom_dep": "COTES-D'ARMOR", "coordonnees": [48.633459, -2.325291], "site_internet": "http://www.hoteltrecelin.com/"}, "geometry": {"type": "Point", "coordinates": [-2.325291, 48.633459]}, "record_timestamp": "2020-07-08T10:30:41.649+02:00"},{"datasetid": "hebergements-classes", "recordid": "64bf0eaebd1c9007a7125782414a62fe11fa69bc", "fields": {"commune": "DINAN", "classement": "3 \u00e9toiles", "categorie": "-", "nom_epci": "CA Dinan Agglom\u00e9ration", "date_de_publication_de_l_etablissement": "2017-06-29", "nom_reg": "BRETAGNE", "courriel": "Contact@avaugourhotel.com", "adresse": "1 Place du Champ Clos", "nom_commercial": "H\u00d4TEL LE D'AVAUGOUR", "date_de_classement": "2017-06-29", "telephone": "0296390749", "capacite_daccueil_personnes": 54, "typologie_etablissement": "H\u00d4TEL", "nombre_de_chambres": 24, "code_postal": "22100", "nom_dep": "COTES-D'ARMOR", "coordonnees": [48.452234, -2.044797], "site_internet": "http://www.avaugourhotel.com"}, "geometry": {"type": "Point", "coordinates": [-2.044797, 48.452234]}, "record_timestamp": "2020-07-08T10:30:41.649+02:00"},{"datasetid": "hebergements-classes", "recordid": "0840087cc89e995e4e284bc0e4d4488c95518305", "fields": {"commune": "LANVOLLON", "classement": "3 \u00e9toiles", "categorie": "-", "nom_epci": "CC Leff Armor Communaut\u00e9", "date_de_publication_de_l_etablissement": "2016-04-12", "nom_reg": "BRETAGNE", "courriel": "lucotel@wanadoo.fr", "adresse": "37 RUE DES FONTAINES", "nom_commercial": "LUCOTEL", "date_de_classement": "2016-04-12", "telephone": "0206700117", "capacite_daccueil_personnes": 70, "typologie_etablissement": "H\u00d4TEL", "nombre_de_chambres": 30, "code_postal": "22290", "nom_dep": "COTES-D'ARMOR", "coordonnees": [48.633342, -2.977536], "site_internet": "http://www.lucotel.com/"}, "geometry": {"type": "Point", "coordinates": [-2.977536, 48.633342]}, "record_timestamp": "2020-07-08T10:30:41.649+02:00"},{"datasetid": "hebergements-classes", "recordid": "c7dbe62987e4068971dbca1ca8e259ca25e77cd1", "fields": {"commune": "PLOUMAGOAR", "classement": "3 \u00e9toiles", "categorie": "-", "nom_epci": "CA Guingamp-Paimpol Armor-Argoat Agglom\u00e9ration", "date_de_publication_de_l_etablissement": "2016-09-10", "nom_reg": "BRETAGNE", "courriel": "nperon@groupesmi.fr", "adresse": "6 rue de la Chesnaye", "nom_commercial": "IBIS GUINGAMP", "date_de_classement": "2016-09-10", "telephone": "0296210941", "capacite_daccueil_personnes": 106, "typologie_etablissement": "H\u00d4TEL", "nombre_de_chambres": 49, "code_postal": "22970", "nom_dep": "COTES-D'ARMOR", "coordonnees": [48.550593, -3.147683], "site_internet": "http://www.ibis.com/fr/france/index.shtml"}, "geometry": {"type": "Point", "coordinates": [-3.147683, 48.550593]}, "record_timestamp": "2020-07-08T10:30:41.649+02:00"},{"datasetid": "hebergements-classes", "recordid": "f44b6a651480f48b9b9770a6c77da82f07fb1fb8", "fields": {"commune": "DINAN", "classement": "3 \u00e9toiles", "categorie": "-", "nom_epci": "CA Dinan Agglom\u00e9ration", "date_de_publication_de_l_etablissement": "2014-02-17", "nom_reg": "BRETAGNE", "courriel": "contact@hotelduchateau-dinan.com", "adresse": "6 rue du ch\u00e2teau", "nom_commercial": "H\u00d4TEL DU CH\u00c2TEAU", "date_de_classement": "2014-02-17", "telephone": "0296851620", "capacite_daccueil_personnes": 84, "typologie_etablissement": "H\u00d4TEL", "nombre_de_chambres": 35, "code_postal": "22100", "nom_dep": "COTES-D'ARMOR", "coordonnees": [48.450086, -2.043587], "site_internet": "www.hotelduchateau-dinan.com"}, "geometry": {"type": "Point", "coordinates": [-2.043587, 48.450086]}, "record_timestamp": "2020-07-08T10:30:41.649+02:00"},{"datasetid": "hebergements-classes", "recordid": "17dfaa715551b7c162a3340ab2b3bfc9f6a5f8c7", "fields": {"commune": "SAINT-LAUNEUC", "classement": "3 \u00e9toiles", "categorie": "-", "nom_epci": "CC Loud\u00e9ac Communaut\u00e9 - Bretagne Centre", "date_de_publication_de_l_etablissement": "2016-07-13", "nom_reg": "BRETAGNE", "courriel": "contact@arduen.com", "adresse": "le bourg", "nom_commercial": "AUBERGE DE LA HARDOUINAIS", "date_de_classement": "2016-07-13", "telephone": "0296561459", "capacite_daccueil_personnes": 40, "typologie_etablissement": "H\u00d4TEL", "nombre_de_chambres": 16, "code_postal": "22230", "nom_dep": "COTES-D'ARMOR", "coordonnees": [48.238934, -2.348527], "site_internet": "www.arduen.com"}, "geometry": {"type": "Point", "coordinates": [-2.348527, 48.238934]}, "record_timestamp": "2020-07-08T10:30:41.649+02:00"},{"datasetid": "hebergements-classes", "recordid": "7f2a91e8967fba2c58270de27c4854c146fda561", "fields": {"commune": "\u00ceLE-DE-BR\u00c9HAT", "classement": "3 \u00e9toiles", "categorie": "-", "date_de_publication_de_l_etablissement": "2017-06-03", "nom_reg": "BRETAGNE", "courriel": "hotelbellevue.brehat@wanadoo.fr", "adresse": "Le Port Clos", "nom_commercial": "H\u00d4TEL BELLEVUE", "date_de_classement": "2017-06-03", "telephone": "0296200005", "capacite_daccueil_personnes": 53, "typologie_etablissement": "H\u00d4TEL", "nombre_de_chambres": 19, "code_postal": "22870", "nom_dep": "COTES-D'ARMOR", "coordonnees": [48.840946, -3.004499], "site_internet": "http://www.hotel-bellevue-brehat.fr"}, "geometry": {"type": "Point", "coordinates": [-3.004499, 48.840946]}, "record_timestamp": "2020-07-08T10:30:41.649+02:00"},{"datasetid": "hebergements-classes", "recordid": "1e2eb678191d3e8183b873a12aebccbcfcb3e125", "fields": {"commune": "FR\u00c9HEL", "classement": "2 \u00e9toiles", "categorie": "-", "nom_epci": "CA Dinan Agglom\u00e9ration", "date_de_publication_de_l_etablissement": "2014-08-13", "nom_reg": "BRETAGNE", "courriel": "aubergelairdevent@orange.fr", "adresse": "25 rue du Calvaire, Pl\u00e9h\u00e9rel Plage", "nom_commercial": "AUBERGE L'AIR DE VENT", "date_de_classement": "2014-08-13", "telephone": "0296414101", "capacite_daccueil_personnes": 17, "typologie_etablissement": "H\u00d4TEL", "nombre_de_chambres": 8, "code_postal": "22240", "nom_dep": "COTES-D'ARMOR", "coordonnees": [48.655041, -2.35728], "site_internet": "http://www.aubergelairdevent.fr/"}, "geometry": {"type": "Point", "coordinates": [-2.35728, 48.655041]}, "record_timestamp": "2020-07-08T10:30:41.649+02:00"},{"datasetid": "hebergements-classes", "recordid": "e96132953cefe87df0e3d00587539e3bf73babff", "fields": {"commune": "DINAN", "classement": "3 \u00e9toiles", "categorie": "-", "nom_epci": "CA Dinan Agglom\u00e9ration", "date_de_publication_de_l_etablissement": "2016-12-12", "nom_reg": "BRETAGNE", "courriel": "hotel-arvor@wanadoo.fr", "adresse": "5 RUE AUGUSTE PAVIE", "nom_commercial": "H\u00d4TEL ARVOR", "date_de_classement": "2016-12-12", "telephone": "0296392122", "capacite_daccueil_personnes": 56, "typologie_etablissement": "H\u00d4TEL", "nombre_de_chambres": 24, "code_postal": "22100", "nom_dep": "COTES-D'ARMOR", "coordonnees": [48.452547, -2.042848], "site_internet": "http://www.hotelarvordinan.com"}, "geometry": {"type": "Point", "coordinates": [-2.042848, 48.452547]}, "record_timestamp": "2020-07-08T10:30:41.649+02:00"},{"datasetid": "hebergements-classes", "recordid": "3811feb05228f1f6ef85141a3926af193301169a", "fields": {"commune": "PERROS-GUIREC", "classement": "3 \u00e9toiles", "categorie": "-", "nom_epci": "CA Lannion-Tr\u00e9gor Communaut\u00e9", "date_de_publication_de_l_etablissement": "2017-05-19", "nom_reg": "BRETAGNE", "courriel": "contact@hotel-les-costans.fr", "adresse": "14 RUE ROUZIC", "nom_commercial": "H\u00d4TEL LES COSTANS", "date_de_classement": "2017-05-19", "telephone": "0296232027", "capacite_daccueil_personnes": 64, "typologie_etablissement": "H\u00d4TEL", "nombre_de_chambres": 27, "code_postal": "22700", "nom_dep": "COTES-D'ARMOR", "coordonnees": [48.817444, -3.443073], "site_internet": "http://www.hotel-les-costans.fr"}, "geometry": {"type": "Point", "coordinates": [-3.443073, 48.817444]}, "record_timestamp": "2020-07-08T10:30:41.649+02:00"},{"datasetid": "hebergements-classes", "recordid": "76f791c9216250d2362e36b913590a3ec2aa0c2a", "fields": {"commune": "SAINT-BRIEUC", "classement": "2 \u00e9toiles", "categorie": "-", "nom_epci": "CA Saint-Brieuc Armor Agglom\u00e9ration", "date_de_publication_de_l_etablissement": "2013-03-18", "nom_reg": "BRETAGNE", "courriel": "hotel.letheatre@wanadoo.fr", "adresse": "17 RUE JOUALLAN", "nom_commercial": "H\u00d4TEL LE THE\u00c2TRE", "date_de_classement": "2013-03-18", "telephone": "0296332318", "capacite_daccueil_personnes": 60, "typologie_etablissement": "H\u00d4TEL", "nombre_de_chambres": 9, "code_postal": "22000", "nom_dep": "COTES-D'ARMOR", "coordonnees": [48.513467, -2.760831], "site_internet": "http://www.hotel-le-theatre.com/"}, "geometry": {"type": "Point", "coordinates": [-2.760831, 48.513467]}, "record_timestamp": "2020-07-08T10:30:41.649+02:00"},{"datasetid": "hebergements-classes", "recordid": "fa97fd56485a6371d20f007b03abeafc767b3e39", "fields": {"commune": "PLOEUC-SUR-LIE", "classement": "2 \u00e9toiles", "categorie": "-", "nom_epci": "CA Saint-Brieuc Armor Agglom\u00e9ration", "date_de_publication_de_l_etablissement": "2015-02-11", "nom_reg": "BRETAGNE", "courriel": "hotelducommerce.ploeuc@orange.fr", "adresse": "21 Place Louis MOREL", "nom_commercial": "H\u00d4TEL RESTAURANT DU COMMERCE", "date_de_classement": "2015-02-11", "telephone": "02 96 42 10 36", "capacite_daccueil_personnes": 27, "typologie_etablissement": "H\u00d4TEL", "nombre_de_chambres": 10, "code_postal": "22150", "nom_dep": "COTES-D'ARMOR", "coordonnees": [48.346296, -2.757333], "site_internet": "-"}, "geometry": {"type": "Point", "coordinates": [-2.757333, 48.346296]}, "record_timestamp": "2020-07-08T10:30:41.649+02:00"},{"datasetid": "hebergements-classes", "recordid": "45a03c7647b63fdb3886013e2ca7edf54f3eff7b", "fields": {"commune": "DINAN", "classement": "3 \u00e9toiles", "categorie": "-", "nom_epci": "CA Dinan Agglom\u00e9ration", "date_de_publication_de_l_etablissement": "2016-04-28", "nom_reg": "BRETAGNE", "courriel": "hotelconnetable@orange.fr", "adresse": "8 Avenue Ren\u00e9 Cassin Quartier de l'Europe", "nom_commercial": "H\u00d4TEL SPA LE CONNETABLE", "date_de_classement": "2016-04-28", "telephone": "0296872929", "capacite_daccueil_personnes": 87, "typologie_etablissement": "H\u00d4TEL", "nombre_de_chambres": 29, "code_postal": "22100", "nom_dep": "COTES-D'ARMOR", "coordonnees": [48.452874, -2.062517], "site_internet": "www.leconnetabledinan.com"}, "geometry": {"type": "Point", "coordinates": [-2.062517, 48.452874]}, "record_timestamp": "2020-07-08T10:30:41.649+02:00"},{"datasetid": "hebergements-classes", "recordid": "41c202318219bddb7b39e470dc0cf1975dff18e3", "fields": {"commune": "SAINT-QUAY-PORTRIEUX", "classement": "4 \u00e9toiles", "categorie": "-", "nom_epci": "CA Saint-Brieuc Armor Agglom\u00e9ration", "date_de_publication_de_l_etablissement": "2017-09-06", "nom_reg": "BRETAGNE", "courriel": "hotelkermoor@orange.fr", "adresse": "13 RUE DU PR\u00c9SIDENT LE SENECAL", "nom_commercial": "H\u00d4TEL KER MOOR PR\u00c9F\u00c9RENCE", "date_de_classement": "2017-09-06", "telephone": "0296705222", "capacite_daccueil_personnes": 60, "typologie_etablissement": "H\u00d4TEL", "nombre_de_chambres": 30, "code_postal": "22410", "nom_dep": "COTES-D'ARMOR", "coordonnees": [48.653934, -2.828628], "site_internet": "http://www.ker-moor.com"}, "geometry": {"type": "Point", "coordinates": [-2.828628, 48.653934]}, "record_timestamp": "2020-07-08T10:30:41.649+02:00"},{"datasetid": "hebergements-classes", "recordid": "1a21367b7d50ae24c7e2ac7028eabd1422f25757", "fields": {"commune": "COLLIN\u00c9E", "classement": "2 \u00e9toiles", "categorie": "-", "nom_epci": "CC Loud\u00e9ac Communaut\u00e9 - Bretagne Centre", "date_de_publication_de_l_etablissement": "2015-04-15", "nom_reg": "BRETAGNE", "courriel": "commault.gilles@wanadoo.fr", "adresse": "5-7 rue du Men\u00e9", "nom_commercial": "H\u00d4TEL LE RELAIS DE MEN\u00c9", "date_de_classement": "2015-04-15", "telephone": "0296314026", "capacite_daccueil_personnes": 25, "typologie_etablissement": "H\u00d4TEL", "nombre_de_chambres": 15, "code_postal": "22330", "nom_dep": "COTES-D'ARMOR", "coordonnees": [48.299931, -2.518312], "site_internet": "http://www.relaisdumene.fr/"}, "geometry": {"type": "Point", "coordinates": [-2.518312, 48.299931]}, "record_timestamp": "2020-07-08T10:30:41.649+02:00"},{"datasetid": "hebergements-classes", "recordid": "129efe84cb1a86c0ef4412dd465b44508e5345e7", "fields": {"commune": "LAMBALLE", "classement": "2 \u00e9toiles", "categorie": "-", "nom_epci": "CA Lamballe Terre et Mer", "date_de_publication_de_l_etablissement": "2017-07-08", "nom_reg": "BRETAGNE", "courriel": "leliondorhotel@wanadoo.fr", "adresse": "3 rue du lion d'or", "nom_commercial": "H\u00d4TEL LE LION D'OR", "date_de_classement": "2017-07-08", "telephone": "0296312036", "capacite_daccueil_personnes": 37, "typologie_etablissement": "H\u00d4TEL", "nombre_de_chambres": 17, "code_postal": "22400", "nom_dep": "COTES-D'ARMOR", "coordonnees": [48.46792, -2.517342], "site_internet": "http://www.leliondor-lamballe.com/"}, "geometry": {"type": "Point", "coordinates": [-2.517342, 48.46792]}, "record_timestamp": "2020-07-08T10:30:41.649+02:00"},{"datasetid": "hebergements-classes", "recordid": "4284b2f6885b2b009142db9e093030427fdae599", "fields": {"commune": "LANGUEUX", "classement": "3 \u00e9toiles", "categorie": "-", "nom_epci": "CA Saint-Brieuc Armor Agglom\u00e9ration", "date_de_publication_de_l_etablissement": "2017-05-07", "nom_reg": "BRETAGNE", "courriel": "saintbrieuc@brithotel.fr", "adresse": "5 RUE DE LA LANDELLE", "nom_commercial": "BRIT H\u00d4TEL SAINT-BRIEUC", "date_de_classement": "2017-05-07", "telephone": "0296524343", "capacite_daccueil_personnes": 182, "typologie_etablissement": "H\u00d4TEL", "nombre_de_chambres": 67, "code_postal": "22360", "nom_dep": "COTES-D'ARMOR", "coordonnees": [48.493949, -2.723286], "site_internet": "www.brithotel.fr/bretagne/saint-brieuc"}, "geometry": {"type": "Point", "coordinates": [-2.723286, 48.493949]}, "record_timestamp": "2020-07-08T10:30:41.649+02:00"},{"datasetid": "hebergements-classes", "recordid": "032c0ed891a30acda5a48bdd6611cd14148e5bc3", "fields": {"commune": "ROSTRENEN", "classement": "2 \u00e9toiles", "categorie": "-", "nom_epci": "CC du Kreiz-Breizh (Cckb)", "date_de_publication_de_l_etablissement": "2017-07-07", "nom_reg": "BRETAGNE", "courriel": "henri4-medicis@wanadoo.fr", "adresse": "ROUTE NATIONALE 164 KERBANEL", "nom_commercial": "H\u00d4TEL LE HENRI IV", "date_de_classement": "2017-07-07", "telephone": "0296291517", "capacite_daccueil_personnes": 71, "typologie_etablissement": "H\u00d4TEL", "nombre_de_chambres": 32, "code_postal": "22110", "nom_dep": "COTES-D'ARMOR", "coordonnees": [48.24085, -3.327047], "site_internet": "http://www.henri4-medicis.com/"}, "geometry": {"type": "Point", "coordinates": [-3.327047, 48.24085]}, "record_timestamp": "2020-07-08T10:30:41.649+02:00"},{"datasetid": "hebergements-classes", "recordid": "36cd713c92241b945736076e47f9e8cbbd714895", "fields": {"commune": "TR\u00c9GUEUX", "classement": "3 \u00e9toiles", "categorie": "-", "nom_epci": "CA Saint-Brieuc Armor Agglom\u00e9ration", "date_de_publication_de_l_etablissement": "2012-10-16", "nom_reg": "BRETAGNE", "courriel": "hotel.leskemm@wanadoo.fr", "adresse": "4 AVENUE PIERRE MEND\u00e8S FRANCE", "nom_commercial": "H\u00d4TEL RESTAURANT L'ESKEMM", "date_de_classement": "2012-10-16", "telephone": "0296784444", "capacite_daccueil_personnes": 115, "typologie_etablissement": "H\u00d4TEL", "nombre_de_chambres": 44, "code_postal": "22950", "nom_dep": "COTES-D'ARMOR", "coordonnees": [48.49287, -2.765089], "site_internet": "http://www.leskemm.com"}, "geometry": {"type": "Point", "coordinates": [-2.765089, 48.49287]}, "record_timestamp": "2020-07-08T10:30:41.649+02:00"},{"datasetid": "hebergements-classes", "recordid": "24e9fbf792df282ec3e0d2babe987b84b6c9aa39", "fields": {"commune": "PERROS-GUIREC", "classement": "3 \u00e9toiles", "categorie": "-", "nom_epci": "CA Lannion-Tr\u00e9gor Communaut\u00e9", "date_de_publication_de_l_etablissement": "2016-04-10", "nom_reg": "BRETAGNE", "courriel": "contact@villaleshydrangeas.bzh", "adresse": "53 boulevard Georges Clemenceau", "nom_commercial": "VILLA LES HYDRANG\u00c9AS", "date_de_classement": "2016-04-10", "telephone": "0296232294", "capacite_daccueil_personnes": 36, "typologie_etablissement": "H\u00d4TEL", "nombre_de_chambres": 16, "code_postal": "22700", "nom_dep": "COTES-D'ARMOR", "coordonnees": [48.818435, -3.438868], "site_internet": "http://villaleshydrangeas.bzh/"}, "geometry": {"type": "Point", "coordinates": [-3.438868, 48.818435]}, "record_timestamp": "2020-07-08T10:30:41.649+02:00"},{"datasetid": "hebergements-classes", "recordid": "ee48e6444b2a921e55a46ed82e237300c2d26a9d", "fields": {"commune": "TADEN", "classement": "3 \u00e9toiles", "categorie": "-", "nom_epci": "CA Dinan Agglom\u00e9ration", "date_de_publication_de_l_etablissement": "2017-05-18", "nom_reg": "BRETAGNE", "courriel": "dinan.taden@campanile.fr", "adresse": "13 Route de Ploubalay", "nom_commercial": "H\u00d4TEL CAMPANILE DINAN TADEN", "date_de_classement": "2017-05-18", "telephone": "0296397565", "capacite_daccueil_personnes": 100, "typologie_etablissement": "H\u00d4TEL", "nombre_de_chambres": 49, "code_postal": "22100", "nom_dep": "COTES-D'ARMOR", "coordonnees": [48.466402, -2.061064], "site_internet": "https://www.campanile.com/fr/hotels/campanile-dinan-taden"}, "geometry": {"type": "Point", "coordinates": [-2.061064, 48.466402]}, "record_timestamp": "2020-07-08T10:30:41.649+02:00"},{"datasetid": "hebergements-classes", "recordid": "9a24c9290f3b5087b9dca16177986972d521ce91", "fields": {"commune": "TR\u00c9BEURDEN", "classement": "2 \u00e9toiles", "categorie": "-", "nom_epci": "CA Lannion-Tr\u00e9gor Communaut\u00e9", "date_de_publication_de_l_etablissement": "2013-04-23", "nom_reg": "BRETAGNE", "courriel": "lequellen@orange.fr", "adresse": "18 Corniche Goas Treiz", "nom_commercial": "LE QUELLEN", "date_de_classement": "2013-04-23", "telephone": "0296154318", "capacite_daccueil_personnes": 20, "typologie_etablissement": "H\u00d4TEL", "nombre_de_chambres": 10, "code_postal": "22560", "nom_dep": "COTES-D'ARMOR", "coordonnees": [48.775663, -3.578649], "site_internet": "http://www.le-quellen.com/"}, "geometry": {"type": "Point", "coordinates": [-3.578649, 48.775663]}, "record_timestamp": "2020-07-08T10:30:41.649+02:00"},{"datasetid": "hebergements-classes", "recordid": "c5d34e7fde0127f6e8834323df6d9ab3306c6811", "fields": {"commune": "DINAN", "classement": "2 \u00e9toiles", "categorie": "-", "nom_epci": "CA Dinan Agglom\u00e9ration", "date_de_publication_de_l_etablissement": "2012-11-14", "nom_reg": "BRETAGNE", "courriel": "hoteldefrancedinan@orange.fr", "adresse": "7 place du 11 novembre 1918", "nom_commercial": "H\u00d4TEL DE FRANCE", "date_de_classement": "2012-11-14", "telephone": "0296392256", "capacite_daccueil_personnes": 32, "typologie_etablissement": "H\u00d4TEL", "nombre_de_chambres": 14, "code_postal": "22100", "nom_dep": "COTES-D'ARMOR", "coordonnees": [48.456441, -2.053129], "site_internet": "http://www.hoteldefrancedinan.fr/topic1/index.html"}, "geometry": {"type": "Point", "coordinates": [-2.053129, 48.456441]}, "record_timestamp": "2020-07-08T10:30:41.649+02:00"},{"datasetid": "hebergements-classes", "recordid": "adc056b14fe00d9ba4dd7b5e4ac2181774edd5ad", "fields": {"commune": "PERROS-GUIREC", "classement": "3 \u00e9toiles", "categorie": "-", "nom_epci": "CA Lannion-Tr\u00e9gor Communaut\u00e9", "date_de_publication_de_l_etablissement": "2014-10-18", "nom_reg": "BRETAGNE", "courriel": "hotel-ker-mor@wanadoo.fr", "adresse": "38 rue du Mar\u00e9chal Foch", "nom_commercial": "H\u00d4TEL KER MOR", "date_de_classement": "2014-10-18", "telephone": "0296231419", "capacite_daccueil_personnes": 60, "typologie_etablissement": "H\u00d4TEL", "nombre_de_chambres": 29, "code_postal": "22700", "nom_dep": "COTES-D'ARMOR", "coordonnees": [48.814921, -3.453399], "site_internet": "hotel-ker-mor.com"}, "geometry": {"type": "Point", "coordinates": [-3.453399, 48.814921]}, "record_timestamp": "2020-07-08T10:30:41.649+02:00"},{"datasetid": "hebergements-classes", "recordid": "d56677b691768d9a436d544d1c5a6d02e6e2da2b", "fields": {"commune": "PERROS-GUIREC", "classement": "3 \u00e9toiles", "categorie": "-", "nom_epci": "CA Lannion-Tr\u00e9gor Communaut\u00e9", "date_de_publication_de_l_etablissement": "2012-01-10", "nom_reg": "BRETAGNE", "courriel": "guegouh@wanadoo.fr", "adresse": "81 rue ernest renan", "nom_commercial": "H\u00d4TEL RESTAURANT LE SUROIT", "date_de_classement": "2012-01-10", "telephone": "0296232383", "capacite_daccueil_personnes": 17, "typologie_etablissement": "H\u00d4TEL", "nombre_de_chambres": 8, "code_postal": "22700", "nom_dep": "COTES-D'ARMOR", "coordonnees": [48.802709, -3.443358], "site_internet": "www.lesuroitperros.com/"}, "geometry": {"type": "Point", "coordinates": [-3.443358, 48.802709]}, "record_timestamp": "2020-07-08T10:30:41.649+02:00"},{"datasetid": "hebergements-classes", "recordid": "4199f1c1684a92b08bd9b9ab68e6c2a2766b2d06", "fields": {"commune": "PL\u00c9RIN", "classement": "3 \u00e9toiles", "categorie": "-", "nom_epci": "CA Saint-Brieuc Armor Agglom\u00e9ration", "date_de_publication_de_l_etablissement": "2012-10-19", "nom_reg": "BRETAGNE", "courriel": "hotel@chenevert22.com", "adresse": "2 RUE DE LA CROIX LORMEL", "nom_commercial": "H\u00d4TEL RESTAURANT AU CH\u00caNE VERT", "date_de_classement": "2012-10-19", "telephone": "0296798020", "capacite_daccueil_personnes": 615, "typologie_etablissement": "H\u00d4TEL", "nombre_de_chambres": 70, "code_postal": "22190", "nom_dep": "COTES-D'ARMOR", "coordonnees": [48.533778, -2.756108], "site_internet": "http://www.hotel-st-brieuc.fr/"}, "geometry": {"type": "Point", "coordinates": [-2.756108, 48.533778]}, "record_timestamp": "2020-07-08T10:30:41.649+02:00"},{"datasetid": "hebergements-classes", "recordid": "3107d4407fb6518a0f816ddc9c58e4e384d38b38", "fields": {"commune": "PERROS -GUIREC", "classement": "2 \u00e9toiles", "categorie": "-", "nom_epci": "CA Lannion-Tr\u00e9gor Communaut\u00e9", "date_de_publication_de_l_etablissement": "2012-12-14", "nom_reg": "BRETAGNE", "courriel": "au-bon-accueil@wanadoo.fr", "adresse": "11 rue de landerval", "nom_commercial": "AU BON ACCUEIL", "date_de_classement": "2012-12-14", "telephone": "0296232411", "capacite_daccueil_personnes": 42, "typologie_etablissement": "H\u00d4TEL", "nombre_de_chambres": 21, "code_postal": "22700", "nom_dep": "COTES-D'ARMOR", "coordonnees": [48.804506, -3.443765], "site_internet": "www.au-bon-accueil.com"}, "geometry": {"type": "Point", "coordinates": [-3.443765, 48.804506]}, "record_timestamp": "2020-07-08T10:30:41.649+02:00"},{"datasetid": "hebergements-classes", "recordid": "aa1a4b3c6b8ec7b531d7b43ec1f195103ebc42e3", "fields": {"commune": "PERROS-GUIREC", "classement": "2 \u00e9toiles", "categorie": "-", "nom_epci": "CA Lannion-Tr\u00e9gor Communaut\u00e9", "date_de_publication_de_l_etablissement": "2013-01-23", "nom_reg": "BRETAGNE", "courriel": "hotelsaint-guirec@wanadoo.fr", "adresse": "plage st guirec ploumanac'h", "nom_commercial": "H\u00d4TEL SAINT GUIREC ET DE LA PLAGE", "date_de_classement": "2013-01-23", "telephone": "0296914089", "capacite_daccueil_personnes": 54, "typologie_etablissement": "H\u00d4TEL", "nombre_de_chambres": 24, "code_postal": "22700", "nom_dep": "COTES-D'ARMOR", "coordonnees": [48.825969, -3.481344], "site_internet": "-"}, "geometry": {"type": "Point", "coordinates": [-3.481344, 48.825969]}, "record_timestamp": "2020-07-08T10:30:41.649+02:00"},{"datasetid": "hebergements-classes", "recordid": "0ca918e3eb5d58255905beeaa36f39b5d24a2524", "fields": {"commune": "PERROS-GUIREC", "classement": "3 \u00e9toiles", "categorie": "-", "nom_epci": "CA Lannion-Tr\u00e9gor Communaut\u00e9", "date_de_publication_de_l_etablissement": "2013-04-23", "nom_reg": "BRETAGNE", "courriel": "lemanoirdusphinx@wanadoo.fr", "adresse": "67 chemin de la messe", "nom_commercial": "LE MANOIR DU SPHINX", "date_de_classement": "2013-04-23", "telephone": "0296232542", "capacite_daccueil_personnes": 41, "typologie_etablissement": "H\u00d4TEL", "nombre_de_chambres": 20, "code_postal": "22700", "nom_dep": "COTES-D'ARMOR", "coordonnees": [48.819791, -3.436404], "site_internet": "lemanoirdusphinx.com"}, "geometry": {"type": "Point", "coordinates": [-3.436404, 48.819791]}, "record_timestamp": "2020-07-08T10:30:41.649+02:00"},{"datasetid": "hebergements-classes", "recordid": "26332840cb4ced7085ac1421a542252a30239ea0", "fields": {"commune": "GUINGAMP", "classement": "3 \u00e9toiles", "categorie": "-", "nom_epci": "CA Guingamp-Paimpol Armor-Argoat Agglom\u00e9ration", "date_de_publication_de_l_etablissement": "2013-01-07", "nom_reg": "BRETAGNE", "courriel": "contact-demeure@wanadoo.fr", "adresse": "5 rue du g\u00e9n\u00e9ral de gaulle", "nom_commercial": "LA DEMEURE", "date_de_classement": "2013-01-07", "telephone": "0296442853", "capacite_daccueil_personnes": 20, "typologie_etablissement": "H\u00d4TEL", "nombre_de_chambres": 10, "code_postal": "22200", "nom_dep": "COTES-D'ARMOR", "coordonnees": [48.562964, -3.15125], "site_internet": "www.demeure-vb.com"}, "geometry": {"type": "Point", "coordinates": [-3.15125, 48.562964]}, "record_timestamp": "2020-07-08T10:30:41.649+02:00"},{"datasetid": "hebergements-classes", "recordid": "debfff370d42383ce2136b520e7996330ecb43e5", "fields": {"commune": "BINIC", "classement": "3 \u00e9toiles", "categorie": "-", "nom_epci": "CA Saint-Brieuc Armor Agglom\u00e9ration", "date_de_publication_de_l_etablissement": "2016-12-23", "nom_reg": "BRETAGNE", "courriel": "hotel@lebenhuyc.com", "adresse": "1 quai jean Bart", "nom_commercial": "H\u00d4TEL LE BENHUYC", "date_de_classement": "2016-12-23", "telephone": "0296787979", "capacite_daccueil_personnes": 56, "typologie_etablissement": "H\u00d4TEL", "nombre_de_chambres": 23, "code_postal": "22520", "nom_dep": "COTES-D'ARMOR", "coordonnees": [48.601504, -2.820919], "site_internet": "www.lebenhuyc.com"}, "geometry": {"type": "Point", "coordinates": [-2.820919, 48.601504]}, "record_timestamp": "2020-07-08T10:30:41.649+02:00"},{"datasetid": "hebergements-classes", "recordid": "0773e91db29192e17eed18ec9a201e0362c326a4", "fields": {"commune": "PERROS-GUIREC", "classement": "2 \u00e9toiles", "categorie": "-", "nom_epci": "CA Lannion-Tr\u00e9gor Communaut\u00e9", "date_de_publication_de_l_etablissement": "2015-04-14", "nom_reg": "BRETAGNE", "courriel": "accueil@hotel-de-perros.fr", "adresse": "28 place de L'h\u00f4tel de ville", "nom_commercial": "H\u00d4TEL DE PERROS", "date_de_classement": "2015-04-14", "telephone": "02.96.23.22.41", "capacite_daccueil_personnes": 42, "typologie_etablissement": "H\u00d4TEL", "nombre_de_chambres": 18, "code_postal": "22700", "nom_dep": "COTES-D'ARMOR", "coordonnees": [48.81587, -3.443807], "site_internet": "http://www.hotel-de-perros.fr/index.php"}, "geometry": {"type": "Point", "coordinates": [-3.443807, 48.81587]}, "record_timestamp": "2020-07-08T10:30:41.649+02:00"},{"datasetid": "hebergements-classes", "recordid": "15f6735f0d9ed67357f34550004214faacb92d5e", "fields": {"commune": "PLOUBAZLANEC", "classement": "4 \u00e9toiles", "categorie": "-", "nom_epci": "CA Guingamp-Paimpol Armor-Argoat Agglom\u00e9ration", "date_de_publication_de_l_etablissement": "2015-05-05", "nom_reg": "BRETAGNE", "courriel": "terrassesdebrehat@orange.fr", "adresse": "Pointe de l'Arcouest", "nom_commercial": "LES TERRASSES DE BREHAT", "date_de_classement": "2015-05-05", "telephone": "0296557792", "capacite_daccueil_personnes": 79, "typologie_etablissement": "H\u00d4TEL", "nombre_de_chambres": 35, "code_postal": "22620", "nom_dep": "COTES-D'ARMOR", "coordonnees": [48.810336, -3.024608], "site_internet": "www.lesterrassesdebrehat.fr"}, "geometry": {"type": "Point", "coordinates": [-3.024608, 48.810336]}, "record_timestamp": "2020-07-08T10:30:41.649+02:00"},{"datasetid": "hebergements-classes", "recordid": "6e119fbaf3d8133c4bbb1553036c4d65f8b7a5a0", "fields": {"commune": "PERROS-GUIREC", "classement": "2 \u00e9toiles", "categorie": "-", "nom_epci": "CA Lannion-Tr\u00e9gor Communaut\u00e9", "date_de_publication_de_l_etablissement": "2012-01-10", "nom_reg": "BRETAGNE", "courriel": "hotel-le-phare@wanadoo.fr", "adresse": "39 rue Saint-Guirec, PLOUMANAC'H", "nom_commercial": "H\u00d4TEL RESTAURANT LE PHARE", "date_de_classement": "2012-01-10", "telephone": "02.96.91.41.19", "capacite_daccueil_personnes": 54, "typologie_etablissement": "H\u00d4TEL", "nombre_de_chambres": 24, "code_postal": "22700", "nom_dep": "COTES-D'ARMOR", "coordonnees": [48.825969, -3.481344], "site_internet": "www.hotel-le-phare.fr"}, "geometry": {"type": "Point", "coordinates": [-3.481344, 48.825969]}, "record_timestamp": "2020-07-08T10:30:41.649+02:00"},{"datasetid": "hebergements-classes", "recordid": "dbdbe54d025e135ee17ba1e7536c2e97af218ae0", "fields": {"commune": "TR\u00c9BEURDEN", "classement": "4 \u00e9toiles", "categorie": "-", "nom_epci": "CA Lannion-Tr\u00e9gor Communaut\u00e9", "date_de_publication_de_l_etablissement": "2014-03-07", "nom_reg": "BRETAGNE", "courriel": "lankerellec@relaischateaux.com", "adresse": "All\u00e9e centrale de Lan Kerellec", "nom_commercial": "MANOIR DE LAN KERELLEC", "date_de_classement": "2014-03-07", "telephone": "02.96.15.00.00", "capacite_daccueil_personnes": 38, "typologie_etablissement": "H\u00d4TEL", "nombre_de_chambres": 19, "code_postal": "22560", "nom_dep": "COTES-D'ARMOR", "coordonnees": [48.777201, -3.583735], "site_internet": "www.lankerellec.com"}, "geometry": {"type": "Point", "coordinates": [-3.583735, 48.777201]}, "record_timestamp": "2020-07-08T10:30:41.649+02:00"},{"datasetid": "hebergements-classes", "recordid": "c4b1a8a4dcac7938693b4b63c90f2310f1674507", "fields": {"commune": "TR\u00c9BEURDEN", "classement": "3 \u00e9toiles", "categorie": "-", "nom_epci": "CA Lannion-Tr\u00e9gor Communaut\u00e9", "date_de_publication_de_l_etablissement": "2014-03-07", "nom_reg": "BRETAGNE", "courriel": "hotelletoeno@gmail.com", "adresse": "56 Corniche de Goas Treiz, Route de Tr\u00e9gastel", "nom_commercial": "H\u00d4TEL LE TO\u00cbNO", "date_de_classement": "2014-03-07", "telephone": "0296236878", "capacite_daccueil_personnes": 36, "typologie_etablissement": "H\u00d4TEL", "nombre_de_chambres": 17, "code_postal": "22560", "nom_dep": "COTES-D'ARMOR", "coordonnees": [48.791651, -3.559777], "site_internet": "www.hoteltoeno.com"}, "geometry": {"type": "Point", "coordinates": [-3.559777, 48.791651]}, "record_timestamp": "2020-07-08T10:30:41.649+02:00"},{"datasetid": "hebergements-classes", "recordid": "653c3661af3515cbf1cb02ed7cc18a9c211a1b91", "fields": {"commune": "SAINT-BRIEUC", "classement": "4 \u00e9toiles", "categorie": "-", "nom_epci": "CA Saint-Brieuc Armor Agglom\u00e9ration", "date_de_publication_de_l_etablissement": "2017-06-30", "nom_reg": "BRETAGNE", "courriel": "novotel.stbrieuc@gmail.com", "adresse": "7 ESPLANADE GEORGES POMPIDOU", "nom_commercial": "H\u00d4TEL NOVOTEL SAINT-BRIEUC CENTRE GARE", "date_de_classement": "2017-06-30", "telephone": "0788222432", "capacite_daccueil_personnes": 243, "typologie_etablissement": "H\u00d4TEL", "nombre_de_chambres": 90, "code_postal": "22000", "nom_dep": "COTES-D'ARMOR", "coordonnees": [48.508633, -2.762196], "site_internet": "https://www.accorhotels.com/fr/hotel-B0L8-novotel-saint-brieuc-centre-gare-opening-may-2017/index.shtml"}, "geometry": {"type": "Point", "coordinates": [-2.762196, 48.508633]}, "record_timestamp": "2020-07-08T10:30:41.649+02:00"},{"datasetid": "hebergements-classes", "recordid": "3de0c0313af007dcc1787563ab383be3976cdfcf", "fields": {"commune": "LANGUEUX", "classement": "3 \u00e9toiles", "categorie": "-", "nom_epci": "CA Saint-Brieuc Armor Agglom\u00e9ration", "date_de_publication_de_l_etablissement": "2017-12-05", "nom_reg": "BRETAGNE", "courriel": "stbrieuc.langueux@campanile.fr", "adresse": "3 RUE DE LA LANDELLE", "nom_commercial": "H\u00d4TEL CAMPANILE SAINT-BRIEUC LANGUEUX", "date_de_classement": "2017-12-05", "telephone": "0296336566", "capacite_daccueil_personnes": 78, "typologie_etablissement": "H\u00d4TEL", "nombre_de_chambres": 39, "code_postal": "22360", "nom_dep": "COTES-D'ARMOR", "coordonnees": [48.494643, -2.72286], "site_internet": "http://www.campanile-saint-brieuc-langueux.fr/fr"}, "geometry": {"type": "Point", "coordinates": [-2.72286, 48.494643]}, "record_timestamp": "2020-07-08T10:30:41.649+02:00"},{"datasetid": "hebergements-classes", "recordid": "729d06920c105c305f0eac6dc3f9ac9e4b138705", "fields": {"commune": "DINAN", "classement": "4 \u00e9toiles", "categorie": "-", "nom_epci": "CA Dinan Agglom\u00e9ration", "date_de_publication_de_l_etablissement": "2014-10-02", "nom_reg": "BRETAGNE", "courriel": "david.prenveille@kyriadrennes.fr", "adresse": "26 quai des talards", "nom_commercial": "BEST WESTERN DINAN LE JERZUAL", "date_de_classement": "2014-10-02", "telephone": "0296870202", "capacite_daccueil_personnes": 110, "typologie_etablissement": "H\u00d4TEL", "nombre_de_chambres": 52, "code_postal": "22100", "nom_dep": "COTES-D'ARMOR", "coordonnees": [48.458675, -2.036915], "site_internet": "http://www.bestwestern.fr/fr/hotel-Dinan,Best-Western-Hotel-Jerzual,93489"}, "geometry": {"type": "Point", "coordinates": [-2.036915, 48.458675]}, "record_timestamp": "2020-07-08T10:30:41.649+02:00"},{"datasetid": "hebergements-classes", "recordid": "a73812cc0c8d4075be060f1d73f23992b57dc9e4", "fields": {"commune": "LANCIEUX", "classement": "3 \u00e9toiles", "categorie": "-", "nom_epci": "CC C\u00f4te d'\u00c9meraude", "date_de_publication_de_l_etablissement": "2016-11-17", "nom_reg": "BRETAGNE", "courriel": "contact@hoteldesbains-lancieux.fr", "adresse": "20 Rue du Poncel", "nom_commercial": "H\u00d4TEL DES BAINS", "date_de_classement": "2016-11-17", "telephone": "0296863133", "capacite_daccueil_personnes": 29, "typologie_etablissement": "H\u00d4TEL", "nombre_de_chambres": 12, "code_postal": "22770", "nom_dep": "COTES-D'ARMOR", "coordonnees": [48.606306, -2.150482], "site_internet": "http://www.hoteldesbains-lancieux.fr/"}, "geometry": {"type": "Point", "coordinates": [-2.150482, 48.606306]}, "record_timestamp": "2020-07-08T10:30:41.649+02:00"},{"datasetid": "hebergements-classes", "recordid": "a7699d1880e5d2fdf302b5389c6d30a9b0039552", "fields": {"commune": "SAINT-BRIEUC", "classement": "2 \u00e9toiles", "categorie": "-", "nom_epci": "CA Saint-Brieuc Armor Agglom\u00e9ration", "date_de_publication_de_l_etablissement": "2014-07-31", "nom_reg": "BRETAGNE", "courriel": "aupotdetain@orange.fr", "adresse": "3 rue de Brest", "nom_commercial": "H\u00d4TEL RESTAURANT AU POT D'\u00c9TAIN", "date_de_classement": "2014-07-31", "telephone": "02 96 77 43 00", "capacite_daccueil_personnes": 22, "typologie_etablissement": "H\u00d4TEL", "nombre_de_chambres": 8, "code_postal": "22000", "nom_dep": "COTES-D'ARMOR", "coordonnees": [48.51183, -2.76643], "site_internet": "http://aupotdetain.e-monsite.com/"}, "geometry": {"type": "Point", "coordinates": [-2.76643, 48.51183]}, "record_timestamp": "2020-07-08T10:30:41.649+02:00"},{"datasetid": "hebergements-classes", "recordid": "075563680480a0d80299e9a0460d2af20e7dc0ae", "fields": {"commune": "QUEMPER-GU\u00c9ZENNEC", "classement": "3 \u00e9toiles", "categorie": "-", "nom_epci": "CA Guingamp-Paimpol Armor-Argoat Agglom\u00e9ration", "date_de_publication_de_l_etablissement": "2012-09-24", "nom_reg": "BRETAGNE", "courriel": "kermodest@live.fr", "adresse": "-", "nom_commercial": "MANOIR DE KERMODEST", "date_de_classement": "2012-09-24", "telephone": "0631391414", "capacite_daccueil_personnes": 40, "typologie_etablissement": "H\u00d4TEL", "nombre_de_chambres": 16, "code_postal": "22260", "nom_dep": "COTES-D'ARMOR", "coordonnees": [48.700964, -3.105857], "site_internet": "http://www.kermodest.com/"}, "geometry": {"type": "Point", "coordinates": [-3.105857, 48.700964]}, "record_timestamp": "2020-07-08T10:30:41.649+02:00"},{"datasetid": "hebergements-classes", "recordid": "1bff39d620e4598a3acb17b9a37a35bdbccab688", "fields": {"commune": "PLOUBAZLANEC", "classement": "2 \u00e9toiles", "categorie": "-", "nom_epci": "CA Guingamp-Paimpol Armor-Argoat Agglom\u00e9ration", "date_de_publication_de_l_etablissement": "2017-10-05", "nom_reg": "BRETAGNE", "courriel": "infos@relaisdelaunay.com", "adresse": "18 route de l'arcouest", "nom_commercial": "H\u00d4TEL LE RELAIS DE LAUNAY", "date_de_classement": "2017-10-05", "telephone": "0296558630", "capacite_daccueil_personnes": 21, "typologie_etablissement": "H\u00d4TEL", "nombre_de_chambres": 9, "code_postal": "22620", "nom_dep": "COTES-D'ARMOR", "coordonnees": [48.809903, -3.024919], "site_internet": "http://www.relaisdelaunay.com"}, "geometry": {"type": "Point", "coordinates": [-3.024919, 48.809903]}, "record_timestamp": "2020-07-08T10:30:41.649+02:00"},{"datasetid": "hebergements-classes", "recordid": "dde3904712df8f23c9a8001ceb40e9e3adee8597", "fields": {"commune": "PLESTIN-LES-GR\u00c8VES", "classement": "2 \u00e9toiles", "categorie": "-", "nom_epci": "CA Lannion-Tr\u00e9gor Communaut\u00e9", "date_de_publication_de_l_etablissement": "2017-01-08", "nom_reg": "BRETAGNE", "courriel": "hotel.les.panoramas@orange.fr", "adresse": "9 rue Poul Guioch", "nom_commercial": "H\u00d4TEL LES PANORAMAS", "date_de_classement": "2017-01-08", "telephone": "0296356376", "capacite_daccueil_personnes": 23, "typologie_etablissement": "H\u00d4TEL", "nombre_de_chambres": 10, "code_postal": "22310", "nom_dep": "COTES-D'ARMOR", "coordonnees": [48.679977, -3.617907], "site_internet": "www.lespanoramas.fr"}, "geometry": {"type": "Point", "coordinates": [-3.617907, 48.679977]}, "record_timestamp": "2020-07-08T10:30:41.649+02:00"},{"datasetid": "hebergements-classes", "recordid": "5db2c291f2f9cb82410248d6d665ebe7b1d42d2e", "fields": {"commune": "DINAN", "classement": "3 \u00e9toiles", "categorie": "-", "nom_epci": "CA Dinan Agglom\u00e9ration", "date_de_publication_de_l_etablissement": "2017-06-04", "nom_reg": "BRETAGNE", "courriel": "lechallonge@wanadoo.fr", "adresse": "29 place duguesclin", "nom_commercial": "H\u00d4TEL LE CHALLONGE", "date_de_classement": "2017-06-04", "telephone": "0296871630", "capacite_daccueil_personnes": 41, "typologie_etablissement": "H\u00d4TEL", "nombre_de_chambres": 18, "code_postal": "22100", "nom_dep": "COTES-D'ARMOR", "coordonnees": [48.45192, -2.044712], "site_internet": "http://www.hotel-dinan.fr"}, "geometry": {"type": "Point", "coordinates": [-2.044712, 48.45192]}, "record_timestamp": "2020-07-08T10:30:41.649+02:00"},{"datasetid": "hebergements-classes", "recordid": "e222f1e7d7082049c678d9d482a7133b65500aa8", "fields": {"commune": "SAINT-BRIEUC", "classement": "3 \u00e9toiles", "categorie": "-", "nom_epci": "CA Saint-Brieuc Armor Agglom\u00e9ration", "date_de_publication_de_l_etablissement": "2016-12-04", "nom_reg": "BRETAGNE", "courriel": "h7475@accor.com", "adresse": "51 RUE DE LA GARE", "nom_commercial": "H\u00d4TEL IBIS STYLES SAINT BRIEUC GARE CENTRE", "date_de_classement": "2016-12-04", "telephone": "0296786996", "capacite_daccueil_personnes": 80, "typologie_etablissement": "H\u00d4TEL", "nombre_de_chambres": 42, "code_postal": "22000", "nom_dep": "COTES-D'ARMOR", "coordonnees": [48.508136, -2.764263], "site_internet": "http://www.ibis.com/fr/hotel-7475-ibis-styles-saint-brieuc-gare-centre/index.shtml"}, "geometry": {"type": "Point", "coordinates": [-2.764263, 48.508136]}, "record_timestamp": "2020-07-08T10:30:41.649+02:00"},{"datasetid": "hebergements-classes", "recordid": "99384ddb2f69673b34070ca76b740ca9e20c7527", "fields": {"commune": "PERROS-GUIREC", "classement": "3 \u00e9toiles", "categorie": "-", "nom_epci": "CA Lannion-Tr\u00e9gor Communaut\u00e9", "date_de_publication_de_l_etablissement": "2016-03-31", "nom_reg": "BRETAGNE", "courriel": "contact@hotel-duparc-perros.com", "adresse": "174 rue saint guirec", "nom_commercial": "HOTEL DU PARC", "date_de_classement": "2016-03-31", "telephone": "0296914080", "capacite_daccueil_personnes": 26, "typologie_etablissement": "H\u00d4TEL", "nombre_de_chambres": 10, "code_postal": "22700", "nom_dep": "COTES-D'ARMOR", "coordonnees": [48.831688, -3.485169], "site_internet": "http://www.hotel-duparc-perros.com"}, "geometry": {"type": "Point", "coordinates": [-3.485169, 48.831688]}, "record_timestamp": "2020-07-08T10:30:41.649+02:00"},{"datasetid": "hebergements-classes", "recordid": "c0fa196e7046096067f6009c71cd378a464352d3", "fields": {"commune": "TR\u00c9GUIER", "classement": "3 \u00e9toiles", "categorie": "-", "nom_epci": "CA Lannion-Tr\u00e9gor Communaut\u00e9", "date_de_publication_de_l_etablissement": "2013-05-22", "nom_reg": "BRETAGNE", "courriel": "aiguemarine@aiguemarine.fr", "adresse": "5 rue Marcelin Berthelot", "nom_commercial": "AIGUE MARINE H\u00d4TEL RESTAURANT", "date_de_classement": "2013-05-22", "telephone": "0296929700", "capacite_daccueil_personnes": 90, "typologie_etablissement": "H\u00d4TEL", "nombre_de_chambres": 48, "code_postal": "22220", "nom_dep": "COTES-D'ARMOR", "coordonnees": [48.787486, -3.224928], "site_internet": "http://www.aiguemarine-hotel.com/"}, "geometry": {"type": "Point", "coordinates": [-3.224928, 48.787486]}, "record_timestamp": "2020-07-08T10:30:41.649+02:00"},{"datasetid": "hebergements-classes", "recordid": "a6531f82873c71e6a453f169d5b3929121993a0e", "fields": {"commune": "MINIHY-TR\u00c9GUIER", "classement": "3 \u00e9toiles", "categorie": "-", "nom_epci": "CA Lannion-Tr\u00e9gor Communaut\u00e9", "date_de_publication_de_l_etablissement": "2013-11-04", "nom_reg": "BRETAGNE", "courriel": "accueil@kastelldinech.com", "adresse": "Route de Lannion, Lieu-Dit Le Castel", "nom_commercial": "H\u00d4TEL KASTELL DINEC'H", "date_de_classement": "2013-11-04", "telephone": "0296929292", "capacite_daccueil_personnes": 36, "typologie_etablissement": "H\u00d4TEL", "nombre_de_chambres": 16, "code_postal": "22220", "nom_dep": "COTES-D'ARMOR", "coordonnees": [48.777467, -3.245189], "site_internet": "www.kastelldinech.com"}, "geometry": {"type": "Point", "coordinates": [-3.245189, 48.777467]}, "record_timestamp": "2020-07-08T10:30:41.649+02:00"},{"datasetid": "hebergements-classes", "recordid": "7243045f90d19fec6d71f0255338efe21ba13450", "fields": {"commune": "SAINT-BRIEUC", "classement": "3 \u00e9toiles", "categorie": "-", "nom_epci": "CA Saint-Brieuc Armor Agglom\u00e9ration", "date_de_publication_de_l_etablissement": "2016-03-08", "nom_reg": "BRETAGNE", "courriel": "direction@hotel-edgar.fr", "adresse": "15 rue Jouallan", "nom_commercial": "H\u00d4TEL EDGAR", "date_de_classement": "2016-03-08", "telephone": "0296602727", "capacite_daccueil_personnes": 62, "typologie_etablissement": "H\u00d4TEL", "nombre_de_chambres": 28, "code_postal": "22000", "nom_dep": "COTES-D'ARMOR", "coordonnees": [48.513572, -2.760712], "site_internet": "http://www.saint-brieuc-hotel.fr/"}, "geometry": {"type": "Point", "coordinates": [-2.760712, 48.513572]}, "record_timestamp": "2020-07-08T10:30:41.649+02:00"},{"datasetid": "hebergements-classes", "recordid": "bfe6e0b6e6f73580b086976a3cb85a3b1f03df73", "fields": {"commune": "LOUD\u00c9AC", "classement": "1 \u00e9toile", "categorie": "-", "nom_epci": "CC Loud\u00e9ac Communaut\u00e9 - Bretagne Centre", "date_de_publication_de_l_etablissement": "2014-10-17", "nom_reg": "BRETAGNE", "courriel": "Lecozannet.dominique@wanadoo.fr", "adresse": "7 rue Louis Lavergne", "nom_commercial": "H\u00d4TEL RESTAURANT LES ROUTIERS", "date_de_classement": "2014-10-17", "telephone": "02 96 28 01 44", "capacite_daccueil_personnes": 48, "typologie_etablissement": "H\u00d4TEL", "nombre_de_chambres": 24, "code_postal": "22600", "nom_dep": "COTES-D'ARMOR", "coordonnees": [48.18069, -2.757102], "site_internet": "-"}, "geometry": {"type": "Point", "coordinates": [-2.757102, 48.18069]}, "record_timestamp": "2020-07-08T10:30:41.649+02:00"},{"datasetid": "hebergements-classes", "recordid": "832416112cb7fd4d4ff917b5a05f050457331fbc", "fields": {"commune": "DINAN", "classement": "1 \u00e9toile", "categorie": "-", "nom_epci": "CA Dinan Agglom\u00e9ration", "date_de_publication_de_l_etablissement": "2013-02-03", "nom_reg": "BRETAGNE", "courriel": "eurl.laura.andrea@orange.fr", "adresse": "10 place duguesclin", "nom_commercial": "LA DUCHESSE ANNE", "date_de_classement": "2013-02-03", "telephone": "0296395976", "capacite_daccueil_personnes": 25, "typologie_etablissement": "H\u00d4TEL", "nombre_de_chambres": 9, "code_postal": "22100", "nom_dep": "COTES-D'ARMOR", "coordonnees": [48.450986, -2.04349], "site_internet": "http://hoteldinanduchessea.monsite-orange.fr/"}, "geometry": {"type": "Point", "coordinates": [-2.04349, 48.450986]}, "record_timestamp": "2020-07-08T10:30:41.649+02:00"},{"datasetid": "hebergements-classes", "recordid": "4b220a82dd91e9c0771eab4b9148081e378e3b97", "fields": {"commune": "LANNION", "classement": "2 \u00e9toiles", "categorie": "-", "nom_epci": "CA Lannion-Tr\u00e9gor Communaut\u00e9", "date_de_publication_de_l_etablissement": "2015-12-21", "nom_reg": "BRETAGNE", "courriel": "hortensias@brithotel.fr", "adresse": "ROUTE DE PERROS GUIREC", "nom_commercial": "BRIT H\u00d4TEL AUX HORTENSIAS", "date_de_classement": "2015-12-21", "telephone": "0296487539", "capacite_daccueil_personnes": 45, "typologie_etablissement": "H\u00d4TEL", "nombre_de_chambres": 16, "code_postal": "22300", "nom_dep": "COTES-D'ARMOR", "coordonnees": [48.762728, -3.451745], "site_internet": "http://lannion.brit-hotel.fr/"}, "geometry": {"type": "Point", "coordinates": [-3.451745, 48.762728]}, "record_timestamp": "2020-07-08T10:30:41.649+02:00"},{"datasetid": "hebergements-classes", "recordid": "4f7b282a29188b791500f66cf2fbda339ba0e6af", "fields": {"commune": "PLOUISY", "classement": "1 \u00e9toile", "categorie": "-", "nom_epci": "CA Guingamp-Paimpol Armor-Argoat Agglom\u00e9ration", "date_de_publication_de_l_etablissement": "2015-04-14", "nom_reg": "BRETAGNE", "courriel": "leterminus.22200@yahoo.fr", "adresse": "9 pont ezer", "nom_commercial": "H\u00d4TEL LE TERMINUS", "date_de_classement": "2015-04-14", "telephone": "0256393870", "capacite_daccueil_personnes": 28, "typologie_etablissement": "H\u00d4TEL", "nombre_de_chambres": 12, "code_postal": "22200", "nom_dep": "COTES-D'ARMOR", "coordonnees": [48.572862, -3.164936], "site_internet": "-"}, "geometry": {"type": "Point", "coordinates": [-3.164936, 48.572862]}, "record_timestamp": "2020-07-08T10:30:41.649+02:00"},{"datasetid": "hebergements-classes", "recordid": "926a3ee22d01a8a0e315dabb80fb8bf95cefac61", "fields": {"commune": "PLOUBAZLANEC", "classement": "2 \u00e9toiles", "categorie": "-", "nom_epci": "CA Guingamp-Paimpol Armor-Argoat Agglom\u00e9ration", "date_de_publication_de_l_etablissement": "2014-07-31", "nom_reg": "BRETAGNE", "courriel": "hotel-bocher@orange.fr", "adresse": "44 RUE PIERRE LOTI", "nom_commercial": "H\u00d4TEL RESTAURANT BOCHER", "date_de_classement": "2014-07-31", "telephone": "0296558416", "capacite_daccueil_personnes": 31, "typologie_etablissement": "H\u00d4TEL", "nombre_de_chambres": 15, "code_postal": "22620", "nom_dep": "COTES-D'ARMOR", "coordonnees": [48.801646, -3.010968], "site_internet": "http://perso.orange.fr/hotelbocher"}, "geometry": {"type": "Point", "coordinates": [-3.010968, 48.801646]}, "record_timestamp": "2020-07-08T10:30:41.649+02:00"},{"datasetid": "hebergements-classes", "recordid": "2baa740c144b8fa7348f075fae696afd4d8c32db", "fields": {"commune": "SAINT-CAST-LE-GUILDO", "classement": "3 \u00e9toiles", "categorie": "-", "nom_epci": "CA Dinan Agglom\u00e9ration", "date_de_publication_de_l_etablissement": "2013-11-04", "nom_reg": "BRETAGNE", "courriel": "lesarcades0614@orange.fr", "adresse": "15 rue du duc d'aiguillon", "nom_commercial": "H\u00d4TEL LES ARCADES", "date_de_classement": "2013-11-04", "telephone": "0296418050", "capacite_daccueil_personnes": 75, "typologie_etablissement": "H\u00d4TEL", "nombre_de_chambres": 32, "code_postal": "22380", "nom_dep": "COTES-D'ARMOR", "coordonnees": [48.634827, -2.256804], "site_internet": "www.hotels-saint-cast.com"}, "geometry": {"type": "Point", "coordinates": [-2.256804, 48.634827]}, "record_timestamp": "2020-07-08T10:30:41.649+02:00"},{"datasetid": "hebergements-classes", "recordid": "73b06cf7614fb55b7d2c693aff6748b872ee3fa7", "fields": {"commune": "PERROS-GUIREC", "classement": "2 \u00e9toiles", "categorie": "-", "nom_epci": "CA Lannion-Tr\u00e9gor Communaut\u00e9", "date_de_publication_de_l_etablissement": "2017-05-30", "nom_reg": "BRETAGNE", "courriel": "hermitage.hotel@wanadoo.fr", "adresse": "20 rue des fr\u00e8res Le Montr\u00e9er", "nom_commercial": "H\u00d4TEL HERMITAGE", "date_de_classement": "2017-05-30", "telephone": "0296232122", "capacite_daccueil_personnes": 32, "typologie_etablissement": "H\u00d4TEL", "nombre_de_chambres": 16, "code_postal": "22700", "nom_dep": "COTES-D'ARMOR", "coordonnees": [48.813896, -3.445743], "site_internet": "http://www.hotelhermitage-22.com"}, "geometry": {"type": "Point", "coordinates": [-3.445743, 48.813896]}, "record_timestamp": "2020-07-08T10:30:41.649+02:00"},{"datasetid": "hebergements-classes", "recordid": "4277ea28c60f97002e5e0cade27c96c283b5eb19", "fields": {"commune": "PERROS-GUIREC", "classement": "3 \u00e9toiles", "categorie": "-", "nom_epci": "CA Lannion-Tr\u00e9gor Communaut\u00e9", "date_de_publication_de_l_etablissement": "2017-03-22", "nom_reg": "BRETAGNE", "courriel": "contact@hotel-les-bains-perros-guirec.fr", "adresse": "100 AVENUE DU CASINO", "nom_commercial": "BEST WESTERN H\u00d4TEL LES BAINS", "date_de_classement": "2017-03-22", "telephone": "0296912211", "capacite_daccueil_personnes": 116, "typologie_etablissement": "H\u00d4TEL", "nombre_de_chambres": 49, "code_postal": "22700", "nom_dep": "COTES-D'ARMOR", "coordonnees": [48.815021, -3.458703], "site_internet": "http://www.hotel-les-bains-perros-guirec.fr/fr/"}, "geometry": {"type": "Point", "coordinates": [-3.458703, 48.815021]}, "record_timestamp": "2020-07-08T10:30:41.649+02:00"},{"datasetid": "hebergements-classes", "recordid": "adad1cbcc0326d8fd6b48f465b286f30288b7fae", "fields": {"commune": "PERROS-GUIREC", "classement": "3 \u00e9toiles", "categorie": "-", "nom_epci": "CA Lannion-Tr\u00e9gor Communaut\u00e9", "date_de_publication_de_l_etablissement": "2017-11-09", "nom_reg": "BRETAGNE", "courriel": "contact@hoteldesrochers.net", "adresse": "70 chemin de la Pointe", "nom_commercial": "H\u00d4TEL DES ROCHERS", "date_de_classement": "2017-11-09", "telephone": "0296916754", "capacite_daccueil_personnes": 36, "typologie_etablissement": "H\u00d4TEL", "nombre_de_chambres": 16, "code_postal": "22700", "nom_dep": "COTES-D'ARMOR", "coordonnees": [48.830035, -3.487718], "site_internet": "www.hotel-desrochers-perros.com"}, "geometry": {"type": "Point", "coordinates": [-3.487718, 48.830035]}, "record_timestamp": "2020-07-08T10:30:41.649+02:00"},{"datasetid": "hebergements-classes", "recordid": "d0ff2fe46d0ae1b4726d5baee93d96cb5fe4707f", "fields": {"commune": "\u00c9TABLES-SUR-MER", "classement": "2 \u00e9toiles", "categorie": "-", "nom_epci": "CA Saint-Brieuc Armor Agglom\u00e9ration", "date_de_publication_de_l_etablissement": "2017-04-25", "nom_reg": "BRETAGNE", "courriel": "hotelheod@wanadoo.fr", "adresse": "All\u00e9e Paul Vatine", "nom_commercial": "H\u00d4TEL HEOD", "date_de_classement": "2017-04-25", "telephone": "0296708282", "capacite_daccueil_personnes": 56, "typologie_etablissement": "H\u00d4TEL", "nombre_de_chambres": 28, "code_postal": "22680", "nom_dep": "COTES-D'ARMOR", "coordonnees": [48.640617, -2.835059], "site_internet": "http://www.heodhotel.com"}, "geometry": {"type": "Point", "coordinates": [-2.835059, 48.640617]}, "record_timestamp": "2020-07-08T10:30:41.649+02:00"},{"datasetid": "hebergements-classes", "recordid": "d09084e3f6af3c44b69d361ba0af588d5d64e021", "fields": {"commune": "TR\u00c9GUEUX", "classement": "1 \u00e9toile", "categorie": "-", "nom_epci": "CA Saint-Brieuc Armor Agglom\u00e9ration", "date_de_publication_de_l_etablissement": "2017-07-25", "nom_reg": "BRETAGNE", "courriel": "stbrieuc@premiereclasse.fr", "adresse": "14 rue Alain Colas", "nom_commercial": "H\u00d4TEL PREMI\u00c8RE CLASSE SAINT BRIEUC TR\u00c9GUEUX", "date_de_classement": "2017-07-25", "telephone": "0296334160", "capacite_daccueil_personnes": 179, "typologie_etablissement": "H\u00d4TEL", "nombre_de_chambres": 72, "code_postal": "22950", "nom_dep": "COTES-D'ARMOR", "coordonnees": [48.490775, -2.72084], "site_internet": "https://www.premiereclasse.com/fr/hotels/premiere-classe-saint-brieuc-tregueux"}, "geometry": {"type": "Point", "coordinates": [-2.72084, 48.490775]}, "record_timestamp": "2020-07-08T10:30:41.649+02:00"},{"datasetid": "hebergements-classes", "recordid": "ef31b31334b4087113d189b43496dd7626c48454", "fields": {"commune": "PL\u00c9NEUF-VAL-ANDR\u00c9", "classement": "2 \u00e9toiles", "categorie": "-", "nom_epci": "CA Lamballe Terre et Mer", "date_de_publication_de_l_etablissement": "2017-10-07", "nom_reg": "BRETAGNE", "courriel": "contact@pleneuf-hoteldefrance.com", "adresse": "4 rue pasteur", "nom_commercial": "H\u00d4TEL DE FRANCE ET DU PETIT PRINCE", "date_de_classement": "2017-10-07", "telephone": "0296722252", "capacite_daccueil_personnes": 38, "typologie_etablissement": "H\u00d4TEL", "nombre_de_chambres": 15, "code_postal": "22370", "nom_dep": "COTES-D'ARMOR", "coordonnees": [48.584424, -2.537475], "site_internet": "http://pleneuf-hoteldefrance.com/"}, "geometry": {"type": "Point", "coordinates": [-2.537475, 48.584424]}, "record_timestamp": "2020-07-08T10:30:41.649+02:00"},{"datasetid": "hebergements-classes", "recordid": "80f02f59aecc5e65f0860feb45ce064b31a5a066", "fields": {"commune": "PLANCO\u00cbT", "classement": "3 \u00e9toiles", "categorie": "-", "nom_epci": "CA Dinan Agglom\u00e9ration", "date_de_publication_de_l_etablissement": "2017-12-09", "nom_reg": "BRETAGNE", "courriel": "contact@maison-crouzil.eu", "adresse": "20 les quais", "nom_commercial": "H\u00d4TEL RESTAURANT L\u2019\u00c9CRIN", "date_de_classement": "2017-12-09", "telephone": "0296841024", "capacite_daccueil_personnes": 12, "typologie_etablissement": "H\u00d4TEL", "nombre_de_chambres": 6, "code_postal": "22130", "nom_dep": "COTES-D'ARMOR", "coordonnees": [48.521473, -2.230124], "site_internet": "http://www.crouzil.com"}, "geometry": {"type": "Point", "coordinates": [-2.230124, 48.521473]}, "record_timestamp": "2020-07-08T10:30:41.649+02:00"},{"datasetid": "hebergements-classes", "recordid": "b9bd9f5bbda256d962862ff04ef018194fac98f6", "fields": {"commune": "PL\u00c9RIN", "classement": "3 \u00e9toiles", "categorie": "-", "nom_epci": "CA Saint-Brieuc Armor Agglom\u00e9ration", "date_de_publication_de_l_etablissement": "2015-09-22", "nom_reg": "BRETAGNE", "courriel": "hid.stbrieuc@gmail.com", "adresse": "33 Rue des Ch\u00eanes", "nom_commercial": "HOTEL INN DESIGN SAINT BRIEUC", "date_de_classement": "2015-09-22", "telephone": "0296792525", "capacite_daccueil_personnes": 94, "typologie_etablissement": "H\u00d4TEL", "nombre_de_chambres": 45, "code_postal": "22190", "nom_dep": "COTES-D'ARMOR", "coordonnees": [48.533964, -2.761136], "site_internet": "http://www.hotel-inn.fr/saint-brieuc"}, "geometry": {"type": "Point", "coordinates": [-2.761136, 48.533964]}, "record_timestamp": "2020-07-08T10:30:41.649+02:00"},{"datasetid": "hebergements-classes", "recordid": "174b485eb2a519588b33dd5cabf6b91340e450af", "fields": {"commune": "PAIMPOL", "classement": "2 \u00e9toiles", "categorie": "-", "nom_epci": "CA Guingamp-Paimpol Armor-Argoat Agglom\u00e9ration", "date_de_publication_de_l_etablissement": "2017-08-17", "nom_reg": "BRETAGNE", "courriel": "contact@legoelo.com", "adresse": "4 QUAI DUGUAY TROUIN", "nom_commercial": "H\u00d4TEL LE GO\u00cbLO", "date_de_classement": "2017-08-17", "telephone": "0296208274", "capacite_daccueil_personnes": 64, "typologie_etablissement": "H\u00d4TEL", "nombre_de_chambres": 32, "code_postal": "22500", "nom_dep": "COTES-D'ARMOR", "coordonnees": [48.779333, -3.044194], "site_internet": "http://www.legoelo.com/"}, "geometry": {"type": "Point", "coordinates": [-3.044194, 48.779333]}, "record_timestamp": "2020-07-08T10:30:41.649+02:00"},{"datasetid": "hebergements-classes", "recordid": "e1ccc67a80cd17ce4d2e8e1b0e24cbdd16115bfc", "fields": {"commune": "L\u00c9HON", "classement": "1 \u00e9toile", "categorie": "-", "nom_epci": "CA Dinan Agglom\u00e9ration", "date_de_publication_de_l_etablissement": "2015-01-04", "nom_reg": "BRETAGNE", "courriel": "hotelleguinefort@gmail.com", "adresse": "5 rue du Guinefort", "nom_commercial": "H\u00d4TEL AUBERGE DU GUINEFORT", "date_de_classement": "2015-01-04", "telephone": "02 96 39 11 85", "capacite_daccueil_personnes": 15, "typologie_etablissement": "H\u00d4TEL", "nombre_de_chambres": 9, "code_postal": "22100", "nom_dep": "COTES-D'ARMOR", "coordonnees": [48.440182, -2.071859], "site_internet": "-"}, "geometry": {"type": "Point", "coordinates": [-2.071859, 48.440182]}, "record_timestamp": "2020-07-08T10:30:41.649+02:00"},{"datasetid": "hebergements-classes", "recordid": "daad13db270cb4a1c082c0aac41839193d4528bf", "fields": {"commune": "SAINT-AGATHON", "classement": "2 \u00e9toiles", "categorie": "-", "nom_epci": "CA Guingamp-Paimpol Armor-Argoat Agglom\u00e9ration", "date_de_publication_de_l_etablissement": "2012-09-10", "nom_reg": "BRETAGNE", "courriel": "dorhotel22@orange.fr", "adresse": "Rue de Kerprad", "nom_commercial": "DOR'H\u00d4TEL", "date_de_classement": "2012-09-10", "telephone": "0296449119", "capacite_daccueil_personnes": 52, "typologie_etablissement": "H\u00d4TEL", "nombre_de_chambres": 18, "code_postal": "22200", "nom_dep": "COTES-D'ARMOR", "coordonnees": [48.559966, -3.127414], "site_internet": "http://www.dorhotel.fr"}, "geometry": {"type": "Point", "coordinates": [-3.127414, 48.559966]}, "record_timestamp": "2020-07-08T10:30:41.649+02:00"},{"datasetid": "hebergements-classes", "recordid": "54ebee829764bc585219c84ca5ded4690704449f", "fields": {"commune": "PLEUMEUR-BODOU", "classement": "3 \u00e9toiles", "categorie": "-", "nom_epci": "CA Lannion-Tr\u00e9gor Communaut\u00e9", "date_de_publication_de_l_etablissement": "2017-01-17", "nom_reg": "BRETAGNE", "courriel": "golf-hotel2@orange.fr", "adresse": "16 Route du Golf", "nom_commercial": "GOLF H\u00d4TEL DE SAINT SAMSON", "date_de_classement": "2017-01-17", "telephone": "0296238734", "capacite_daccueil_personnes": 112, "typologie_etablissement": "H\u00d4TEL", "nombre_de_chambres": 50, "code_postal": "22560", "nom_dep": "COTES-D'ARMOR", "coordonnees": [48.804612, -3.520786], "site_internet": "http://www.golfhotel-saint-samson.com"}, "geometry": {"type": "Point", "coordinates": [-3.520786, 48.804612]}, "record_timestamp": "2020-07-08T10:30:41.649+02:00"},{"datasetid": "hebergements-classes", "recordid": "ac273627384f92f420abd67d6798f5ccff93cb49", "fields": {"commune": "PERROS-GUIREC", "classement": "2 \u00e9toiles", "categorie": "-", "nom_epci": "CA Lannion-Tr\u00e9gor Communaut\u00e9", "date_de_publication_de_l_etablissement": "2017-05-31", "nom_reg": "BRETAGNE", "courriel": "contact@hoteldeleurope-perros.com", "adresse": "158 Rue Saint-Guirec", "nom_commercial": "H\u00d4TEL DE L'EUROPE", "date_de_classement": "2017-05-31", "telephone": "0296914076", "capacite_daccueil_personnes": 50, "typologie_etablissement": "H\u00d4TEL", "nombre_de_chambres": 23, "code_postal": "22700", "nom_dep": "COTES-D'ARMOR", "coordonnees": [48.831903, -3.486032], "site_internet": "http://www.hoteldeleurope-perros.com"}, "geometry": {"type": "Point", "coordinates": [-3.486032, 48.831903]}, "record_timestamp": "2020-07-08T10:30:41.649+02:00"},{"datasetid": "hebergements-classes", "recordid": "1d7bec62dd2cb7faf872ef2be91c612a414382db", "fields": {"commune": "DINAN", "classement": "3 \u00e9toiles", "categorie": "-", "nom_epci": "CA Dinan Agglom\u00e9ration", "date_de_publication_de_l_etablissement": "2017-01-31", "nom_reg": "BRETAGNE", "courriel": "h5977@accor.com", "adresse": "1 PLACE DUCLOS PINOT", "nom_commercial": "H\u00d4TEL IBIS STYLES DINAN CENTRE VILLE", "date_de_classement": "2017-01-31", "telephone": "0296394615", "capacite_daccueil_personnes": 142, "typologie_etablissement": "H\u00d4TEL", "nombre_de_chambres": 62, "code_postal": "22100", "nom_dep": "COTES-D'ARMOR", "coordonnees": [48.454257, -2.048957], "site_internet": "http://www.accorhotels.com/fr/hotel-5977-ibis-styles-dinan-centre-ville-ex-ibis/index.shtml"}, "geometry": {"type": "Point", "coordinates": [-2.048957, 48.454257]}, "record_timestamp": "2020-07-08T10:30:41.649+02:00"},{"datasetid": "hebergements-classes", "recordid": "b8a606addc4f6b3d316821f19c2cac30ad25ae9c", "fields": {"commune": "SAINT-AGATHON", "classement": "2 \u00e9toiles", "categorie": "-", "nom_epci": "CA Guingamp-Paimpol Armor-Argoat Agglom\u00e9ration", "date_de_publication_de_l_etablissement": "2016-01-04", "nom_reg": "BRETAGNE", "courriel": "aurelaisdebellevue@orange.fr", "adresse": "1 rue de bellevue RN 12", "nom_commercial": "H\u00d4TEL AU RELAIS DE BELLEVUE", "date_de_classement": "2016-01-04", "telephone": "0296438053", "capacite_daccueil_personnes": 40, "typologie_etablissement": "H\u00d4TEL", "nombre_de_chambres": 18, "code_postal": "22200", "nom_dep": "COTES-D'ARMOR", "coordonnees": [48.555111, -3.119209], "site_internet": "http://www.relaisbellevue.fr"}, "geometry": {"type": "Point", "coordinates": [-3.119209, 48.555111]}, "record_timestamp": "2020-07-08T10:30:41.649+02:00"},{"datasetid": "hebergements-classes", "recordid": "41f3b6cad871d6afd14e450e4141d08d81326397", "fields": {"commune": "GLOMEL", "classement": "2 \u00e9toiles", "categorie": "-", "nom_epci": "CC du Kreiz-Breizh (Cckb)", "date_de_publication_de_l_etablissement": "2013-07-01", "nom_reg": "BRETAGNE", "courriel": "lacascade22@orange.fr", "adresse": "5 grande rue", "nom_commercial": "AUBERGE LA CASCADE", "date_de_classement": "2013-07-01", "telephone": "0296296044", "capacite_daccueil_personnes": 16, "typologie_etablissement": "H\u00d4TEL", "nombre_de_chambres": 8, "code_postal": "22110", "nom_dep": "COTES-D'ARMOR", "coordonnees": [48.222843, -3.395066], "site_internet": "-"}, "geometry": {"type": "Point", "coordinates": [-3.395066, 48.222843]}, "record_timestamp": "2020-07-08T10:30:41.649+02:00"},{"datasetid": "hebergements-classes", "recordid": "ffb35b5c09a785287151944cdae3ef1ea12babf3", "fields": {"commune": "PLOUBAZLANEC", "classement": "3 \u00e9toiles", "categorie": "-", "nom_epci": "CA Guingamp-Paimpol Armor-Argoat Agglom\u00e9ration", "date_de_publication_de_l_etablissement": "2017-07-26", "nom_reg": "BRETAGNE", "courriel": "contact@hotel-les-agapanthes.com", "adresse": "1 rue Adrien Rebours", "nom_commercial": "H\u00d4TEL LES AGAPANTHES", "date_de_classement": "2017-07-26", "telephone": "0296558906", "capacite_daccueil_personnes": 47, "typologie_etablissement": "H\u00d4TEL", "nombre_de_chambres": 20, "code_postal": "22620", "nom_dep": "COTES-D'ARMOR", "coordonnees": [48.801422, -3.031805], "site_internet": "http://www.hotel-les-agapanthes.com"}, "geometry": {"type": "Point", "coordinates": [-3.031805, 48.801422]}, "record_timestamp": "2020-07-08T10:30:41.649+02:00"},{"datasetid": "hebergements-classes", "recordid": "6f42fc07c31383b5ef819ed54b759f5c4a47f702", "fields": {"commune": "PAIMPOL", "classement": "3 \u00e9toiles", "categorie": "-", "nom_epci": "CA Guingamp-Paimpol Armor-Argoat Agglom\u00e9ration", "date_de_publication_de_l_etablissement": "2014-08-13", "nom_reg": "BRETAGNE", "courriel": "hoteldelamarne@orange.fr", "adresse": "30 rue de la Marne", "nom_commercial": "H\u00d4TEL DE LA MARNE", "date_de_classement": "2014-08-13", "telephone": "0296163341", "capacite_daccueil_personnes": 20, "typologie_etablissement": "H\u00d4TEL", "nombre_de_chambres": 9, "code_postal": "22500", "nom_dep": "COTES-D'ARMOR", "coordonnees": [48.776305, -3.049621], "site_internet": "www.hoteldelamarne-paimpol.fr"}, "geometry": {"type": "Point", "coordinates": [-3.049621, 48.776305]}, "record_timestamp": "2020-07-08T10:30:41.649+02:00"},{"datasetid": "hebergements-classes", "recordid": "0e35a57996bbf981177184db09904abbbbc22d75", "fields": {"commune": "TR\u00c9GUIER", "classement": "2 \u00e9toiles", "categorie": "-", "nom_epci": "CA Lannion-Tr\u00e9gor Communaut\u00e9", "date_de_publication_de_l_etablissement": "2016-03-31", "nom_reg": "BRETAGNE", "courriel": "lesaintyvestreguier@gmail.com", "adresse": "4 rue colvestre", "nom_commercial": "H\u00d4TEL LE SAINT-YVES", "date_de_classement": "2016-03-31", "telephone": "02 96 92 33 49", "capacite_daccueil_personnes": 18, "typologie_etablissement": "H\u00d4TEL", "nombre_de_chambres": 8, "code_postal": "22220", "nom_dep": "COTES-D'ARMOR", "coordonnees": [48.787815, -3.23168], "site_internet": "http://www.lesaintyvestreguier.com/"}, "geometry": {"type": "Point", "coordinates": [-3.23168, 48.787815]}, "record_timestamp": "2020-07-08T10:30:41.649+02:00"},{"datasetid": "hebergements-classes", "recordid": "887d9af14a35e1d0f9c4358bb5a7774fc4b370ae", "fields": {"commune": "BINIC", "classement": "3 \u00e9toiles", "categorie": "-", "nom_epci": "CA Saint-Brieuc Armor Agglom\u00e9ration", "date_de_publication_de_l_etablissement": "2013-07-29", "nom_reg": "BRETAGNE", "courriel": "victoria-binic@orange.fr", "adresse": "les fontaines gicquel", "nom_commercial": "BRIT HOTEL BINIC", "date_de_classement": "2013-07-29", "telephone": "0296323780", "capacite_daccueil_personnes": 80, "typologie_etablissement": "H\u00d4TEL", "nombre_de_chambres": 40, "code_postal": "22520", "nom_dep": "COTES-D'ARMOR", "coordonnees": [48.611874, -2.833225], "site_internet": "http://www.brithotel.fr/"}, "geometry": {"type": "Point", "coordinates": [-2.833225, 48.611874]}, "record_timestamp": "2020-07-08T10:30:41.649+02:00"},{"datasetid": "hebergements-classes", "recordid": "2dea6bce4af39751399b17824baa9c87136484c6", "fields": {"commune": "PERROS-GUIREC", "classement": "2 \u00e9toiles", "categorie": "-", "nom_epci": "CA Lannion-Tr\u00e9gor Communaut\u00e9", "date_de_publication_de_l_etablissement": "2017-03-22", "nom_reg": "BRETAGNE", "courriel": "bienvenue@sternes.com", "adresse": "Rond point de Perros", "nom_commercial": "H\u00d4TEL LES STERNES", "date_de_classement": "2017-03-22", "telephone": "0296910238", "capacite_daccueil_personnes": 55, "typologie_etablissement": "H\u00d4TEL", "nombre_de_chambres": 20, "code_postal": "22700", "nom_dep": "COTES-D'ARMOR", "coordonnees": [48.807001, -3.461507], "site_internet": "http://www.sternes.com"}, "geometry": {"type": "Point", "coordinates": [-3.461507, 48.807001]}, "record_timestamp": "2020-07-08T10:30:41.649+02:00"},{"datasetid": "hebergements-classes", "recordid": "a9e976e4a825afef467518f821384cac10b0f29e", "fields": {"commune": "TR\u00c9GASTEL", "classement": "3 \u00e9toiles", "categorie": "-", "nom_epci": "CA Lannion-Tr\u00e9gor Communaut\u00e9", "date_de_publication_de_l_etablissement": "2015-07-22", "nom_reg": "BRETAGNE", "courriel": "daniel.laveant@orange.fr", "adresse": "5 plage du Coz Pors", "nom_commercial": "H\u00d4TEL BEAUS\u00c9JOUR", "date_de_classement": "2015-07-22", "telephone": "02 96 23 88 02", "capacite_daccueil_personnes": 25, "typologie_etablissement": "H\u00d4TEL", "nombre_de_chambres": 10, "code_postal": "22730", "nom_dep": "COTES-D'ARMOR", "coordonnees": [48.83285, -3.514954], "site_internet": "http://www.beausejoursarl.com/"}, "geometry": {"type": "Point", "coordinates": [-3.514954, 48.83285]}, "record_timestamp": "2020-07-08T10:30:41.649+02:00"},{"datasetid": "hebergements-classes", "recordid": "821db3fcf941cc87834faac37b890c4fa20a76a3", "fields": {"commune": "SAINT-BRIEUC", "classement": "2 \u00e9toiles", "categorie": "-", "nom_epci": "CA Saint-Brieuc Armor Agglom\u00e9ration", "date_de_publication_de_l_etablissement": "2017-05-29", "nom_reg": "BRETAGNE", "courriel": "hoteldemars@wanadoo.fr", "adresse": "13 rue du G\u00e9n\u00e9ral Leclerc", "nom_commercial": "H\u00d4TEL DU CHAMP DE MARS", "date_de_classement": "2017-05-29", "telephone": "0296336099", "capacite_daccueil_personnes": 42, "typologie_etablissement": "H\u00d4TEL", "nombre_de_chambres": 21, "code_postal": "22000", "nom_dep": "COTES-D'ARMOR", "coordonnees": [48.512343, -2.760364], "site_internet": "http://www.hotel-saint-brieuc.fr"}, "geometry": {"type": "Point", "coordinates": [-2.760364, 48.512343]}, "record_timestamp": "2020-07-08T10:30:41.649+02:00"},{"datasetid": "hebergements-classes", "recordid": "3cf6dbd5ed294e362c40c0b6c185f0a1e9f8037d", "fields": {"commune": "PL\u00c9NEUF-VAL-ANDR\u00c9", "classement": "3 \u00e9toiles", "categorie": "-", "nom_epci": "CA Lamballe Terre et Mer", "date_de_publication_de_l_etablissement": "2015-10-06", "nom_reg": "BRETAGNE", "courriel": "hdlm2@wanadoo.fr", "adresse": "63 rue Amiral Charner", "nom_commercial": "H\u00d4TEL DE LA MER", "date_de_classement": "2015-10-06", "telephone": "0296722044", "capacite_daccueil_personnes": 27, "typologie_etablissement": "H\u00d4TEL", "nombre_de_chambres": 13, "code_postal": "22370", "nom_dep": "COTES-D'ARMOR", "coordonnees": [48.586248, -2.557976], "site_internet": "http://www.hotelduvalandre.fr/"}, "geometry": {"type": "Point", "coordinates": [-2.557976, 48.586248]}, "record_timestamp": "2020-07-08T10:30:41.649+02:00"},{"datasetid": "hebergements-classes", "recordid": "26519aa6808180c09f92fd2b3546a87c0d1804bc", "fields": {"commune": "YFFINIAC", "classement": "3 \u00e9toiles", "categorie": "-", "nom_epci": "CA Saint-Brieuc Armor Agglom\u00e9ration", "date_de_publication_de_l_etablissement": "2017-05-01", "nom_reg": "BRETAGNE", "courriel": "H1755@ACCOR.COM", "adresse": "36 RUE JULIEN QUINTIN", "nom_commercial": "H\u00d4TEL IBIS SAINT BRIEUC YFFINIAC", "date_de_classement": "2017-05-01", "telephone": "0296726410", "capacite_daccueil_personnes": 84, "typologie_etablissement": "H\u00d4TEL", "nombre_de_chambres": 42, "code_postal": "22120", "nom_dep": "COTES-D'ARMOR", "coordonnees": [48.480415, -2.66414], "site_internet": "http://www.accorhotels.com/fr/hotel-1755-ibis-saint-brieuc-yffiniac/index.shtml"}, "geometry": {"type": "Point", "coordinates": [-2.66414, 48.480415]}, "record_timestamp": "2020-07-08T10:30:41.649+02:00"},{"datasetid": "hebergements-classes", "recordid": "bff5dc8a4b4ecae41d915aa6956d4c3b550baf59", "fields": {"commune": "PAIMPOL", "classement": "2 \u00e9toiles", "categorie": "-", "nom_epci": "CA Guingamp-Paimpol Armor-Argoat Agglom\u00e9ration", "date_de_publication_de_l_etablissement": "2014-08-13", "nom_reg": "BRETAGNE", "courriel": "didier.le.graet@orange.fr", "adresse": "33 rue de goas plat", "nom_commercial": "H\u00d4TEL LE GOAS PLAT", "date_de_classement": "2014-08-13", "telephone": "0296209354", "capacite_daccueil_personnes": 25, "typologie_etablissement": "H\u00d4TEL", "nombre_de_chambres": 19, "code_postal": "22500", "nom_dep": "COTES-D'ARMOR", "coordonnees": [48.774138, -3.043122], "site_internet": "http://www.hotel-legoasplat-paimpol.fr"}, "geometry": {"type": "Point", "coordinates": [-3.043122, 48.774138]}, "record_timestamp": "2020-07-08T10:30:41.649+02:00"},{"datasetid": "hebergements-classes", "recordid": "0086f5aa428dbcc90192a7fe3bc118504ae5b201", "fields": {"commune": "PL\u00c9RIN", "classement": "2 \u00e9toiles", "categorie": "-", "nom_epci": "CA Saint-Brieuc Armor Agglom\u00e9ration", "date_de_publication_de_l_etablissement": "2015-04-17", "nom_reg": "BRETAGNE", "courriel": "hotellagrandvoile@hotmail.com", "adresse": "5 rue de la Poste", "nom_commercial": "H\u00d4TEL BAR RESTAURANT LA GRAND' VOILE", "date_de_classement": "2015-04-17", "telephone": "02 96 33 10 16", "capacite_daccueil_personnes": 31, "typologie_etablissement": "H\u00d4TEL", "nombre_de_chambres": 12, "code_postal": "22190", "nom_dep": "COTES-D'ARMOR", "coordonnees": [48.525004, -2.745445], "site_internet": "-"}, "geometry": {"type": "Point", "coordinates": [-2.745445, 48.525004]}, "record_timestamp": "2020-07-08T10:30:41.649+02:00"},{"datasetid": "hebergements-classes", "recordid": "4e843b946bbb03b41745d8a0ccc5d03637da2316", "fields": {"commune": "PENV\u00c9NAN", "classement": "2 \u00e9toiles", "categorie": "-", "nom_epci": "CA Lannion-Tr\u00e9gor Communaut\u00e9", "date_de_publication_de_l_etablissement": "2015-04-14", "nom_reg": "BRETAGNE", "courriel": "legrandhoteldeportblanc@gmail.com", "adresse": "1 boulevard de la Mer", "nom_commercial": "LE GRAND H\u00d4TEL DE PORT-BLANC", "date_de_classement": "2015-04-14", "telephone": "02 96 92 66 52", "capacite_daccueil_personnes": 50, "typologie_etablissement": "H\u00d4TEL", "nombre_de_chambres": 21, "code_postal": "22710", "nom_dep": "COTES-D'ARMOR", "coordonnees": [48.836182, -3.312701], "site_internet": "http://www.grandhotelportblanc.com/accueil.html"}, "geometry": {"type": "Point", "coordinates": [-3.312701, 48.836182]}, "record_timestamp": "2020-07-08T10:30:41.649+02:00"},{"datasetid": "hebergements-classes", "recordid": "24dacb1343e943aff3b84d1ce5a22c6dcbb12fa1", "fields": {"commune": "SAINT-QUAY-PORTRIEUX", "classement": "2 \u00e9toiles", "categorie": "-", "nom_epci": "CA Saint-Brieuc Armor Agglom\u00e9ration", "date_de_publication_de_l_etablissement": "2014-07-31", "nom_reg": "BRETAGNE", "courriel": "gerbotdavoine@wanadoo.fr", "adresse": "2 Boulevard du Littoral", "nom_commercial": "H\u00d4TEL LE GERBOT D'AVOINE", "date_de_classement": "2014-07-31", "telephone": "02 96 70 40 09", "capacite_daccueil_personnes": 40, "typologie_etablissement": "H\u00d4TEL", "nombre_de_chambres": 19, "code_postal": "22410", "nom_dep": "COTES-D'ARMOR", "coordonnees": [48.656904, -2.839741], "site_internet": "http://www.gerbotdavoine.com/"}, "geometry": {"type": "Point", "coordinates": [-2.839741, 48.656904]}, "record_timestamp": "2020-07-08T10:30:41.649+02:00"},{"datasetid": "hebergements-classes", "recordid": "8a9d8df4b1ce551e26371fc8f0e0252232b28235", "fields": {"commune": "PLOU\u00cbR-SUR-RANCE", "classement": "3 \u00e9toiles", "categorie": "-", "nom_epci": "CA Dinan Agglom\u00e9ration", "date_de_publication_de_l_etablissement": "2016-06-17", "nom_reg": "BRETAGNE", "courriel": "hotel.rigourdaine@wanadoo.fr", "adresse": "MANOIR DE RIGOURDAINE", "nom_commercial": "H\u00d4TEL MANOIR DE RIGOURDAINE", "date_de_classement": "2016-06-17", "telephone": "0296868996", "capacite_daccueil_personnes": 51, "typologie_etablissement": "H\u00d4TEL", "nombre_de_chambres": 19, "code_postal": "22490", "nom_dep": "COTES-D'ARMOR", "coordonnees": [48.547367, -1.993788], "site_internet": "http://www.hotel-rigourdaine.fr"}, "geometry": {"type": "Point", "coordinates": [-1.993788, 48.547367]}, "record_timestamp": "2020-07-08T10:30:41.649+02:00"},{"datasetid": "hebergements-classes", "recordid": "a606af03f90a072801c224f31ec0e85186fc1d6c", "fields": {"commune": "TR\u00c9V\u00c9", "classement": "2 \u00e9toiles", "categorie": "-", "nom_epci": "CC Loud\u00e9ac Communaut\u00e9 - Bretagne Centre", "date_de_publication_de_l_etablissement": "2014-09-24", "nom_reg": "BRETAGNE", "courriel": "info@genetsdor.fr", "adresse": "1 rue Jean Sohier", "nom_commercial": "H\u00d4TEL LES GEN\u00caTS D'OR", "date_de_classement": "2014-09-24", "telephone": "02 96 25 00 25", "capacite_daccueil_personnes": 20, "typologie_etablissement": "H\u00d4TEL", "nombre_de_chambres": 10, "code_postal": "22600", "nom_dep": "COTES-D'ARMOR", "coordonnees": [48.212437, -2.794793], "site_internet": "http://www.genetsdor.fr/"}, "geometry": {"type": "Point", "coordinates": [-2.794793, 48.212437]}, "record_timestamp": "2020-07-08T10:30:41.649+02:00"},{"datasetid": "hebergements-classes", "recordid": "942661cea7ffd8864cd09c770415a64ede683fbb", "fields": {"commune": "FR\u00c9HEL", "classement": "2 \u00e9toiles", "categorie": "-", "nom_epci": "CA Dinan Agglom\u00e9ration", "date_de_publication_de_l_etablissement": "2012-11-14", "nom_reg": "BRETAGNE", "courriel": "manoir-st-michel@fournel.de", "adresse": "38 rue de la carquois", "nom_commercial": "H\u00d4TEL LE MANOIR SAINT-MICHEL", "date_de_classement": "2012-11-14", "telephone": "0296414887", "capacite_daccueil_personnes": 54, "typologie_etablissement": "H\u00d4TEL", "nombre_de_chambres": 20, "code_postal": "22240", "nom_dep": "COTES-D'ARMOR", "coordonnees": [48.642887, -2.388907], "site_internet": "http://www.hotel-bretagne.de"}, "geometry": {"type": "Point", "coordinates": [-2.388907, 48.642887]}, "record_timestamp": "2020-07-08T10:30:41.649+02:00"},{"datasetid": "hebergements-classes", "recordid": "e4d4e2efd248175a3c62ef2c58edf712b310c257", "fields": {"commune": "PERROS-GUIREC", "classement": "5 \u00e9toiles", "categorie": "-", "nom_epci": "CA Lannion-Tr\u00e9gor Communaut\u00e9", "date_de_publication_de_l_etablissement": "2016-09-19", "nom_reg": "BRETAGNE", "courriel": "reservation@lagapa.com", "adresse": "12 Rue des Bons Enfants", "nom_commercial": "L'AGAPA H\u00d4TEL SPA", "date_de_classement": "2016-09-19", "telephone": "0296490110", "capacite_daccueil_personnes": 94, "typologie_etablissement": "H\u00d4TEL", "nombre_de_chambres": 45, "code_postal": "22700", "nom_dep": "COTES-D'ARMOR", "coordonnees": [48.814117, -3.45032], "site_internet": "http://www.lagapa.com/"}, "geometry": {"type": "Point", "coordinates": [-3.45032, 48.814117]}, "record_timestamp": "2020-07-08T10:30:41.649+02:00"},{"datasetid": "hebergements-classes", "recordid": "e1fd36ab14bbc9a75904aa79b787c102d559d17f", "fields": {"commune": "TR\u00c9GUEUX", "classement": "1 \u00e9toile", "categorie": "-", "nom_epci": "CA Saint-Brieuc Armor Agglom\u00e9ration", "date_de_publication_de_l_etablissement": "2012-12-20", "nom_reg": "BRETAGNE", "courriel": "saint-brieuc@quickpalace.com", "adresse": "La Hazaie, Rue Alain Colas", "nom_commercial": "QUICK PALACE", "date_de_classement": "2012-12-20", "telephone": "0296522110", "capacite_daccueil_personnes": 67, "typologie_etablissement": "H\u00d4TEL", "nombre_de_chambres": 35, "code_postal": "22950", "nom_dep": "COTES-D'ARMOR", "coordonnees": [48.491056, -2.721076], "site_internet": "www.quickpalace.com"}, "geometry": {"type": "Point", "coordinates": [-2.721076, 48.491056]}, "record_timestamp": "2020-07-08T10:30:41.649+02:00"},{"datasetid": "hebergements-classes", "recordid": "b334a98076025f3d27b991d61f273059bdd4bd4e", "fields": {"commune": "L\u00c9ZARDRIEUX", "classement": "2 \u00e9toiles", "categorie": "-", "nom_epci": "CA Lannion-Tr\u00e9gor Communaut\u00e9", "date_de_publication_de_l_etablissement": "2014-10-18", "nom_reg": "BRETAGNE", "courriel": "lelittoral.lezardrieux@wanadoo.fr", "adresse": "8 rue Saint-Christophe", "nom_commercial": "H\u00d4TEL LE LITTORAL", "date_de_classement": "2014-10-18", "telephone": "0296201059", "capacite_daccueil_personnes": 30, "typologie_etablissement": "H\u00d4TEL", "nombre_de_chambres": 15, "code_postal": "22740", "nom_dep": "COTES-D'ARMOR", "coordonnees": [48.784225, -3.106335], "site_internet": "http://www.hotel-lelittoral.com"}, "geometry": {"type": "Point", "coordinates": [-3.106335, 48.784225]}, "record_timestamp": "2020-07-08T10:30:41.649+02:00"},{"datasetid": "hebergements-classes", "recordid": "2238aff832554bd9fbdd1419724469f839408332", "fields": {"commune": "ERQUY", "classement": "3 \u00e9toiles", "categorie": "-", "nom_epci": "CA Lamballe Terre et Mer", "date_de_publication_de_l_etablissement": "2017-07-17", "nom_reg": "BRETAGNE", "courriel": "hotel.beausejour@wanadoo.fr", "adresse": "21 RUE DE LA CORNICHE", "nom_commercial": "H\u00d4TEL BEAUS\u00c9JOUR", "date_de_classement": "2017-07-17", "telephone": "0663054580", "capacite_daccueil_personnes": 34, "typologie_etablissement": "H\u00d4TEL", "nombre_de_chambres": 16, "code_postal": "22430", "nom_dep": "COTES-D'ARMOR", "coordonnees": [48.628448, -2.469028], "site_internet": "http://beausejour-erquy.com"}, "geometry": {"type": "Point", "coordinates": [-2.469028, 48.628448]}, "record_timestamp": "2020-07-08T10:30:41.649+02:00"},{"datasetid": "hebergements-classes", "recordid": "46fc514b6990a9a3b54b0636fea0c7570dda9769", "fields": {"commune": "HILLION", "classement": "2 \u00e9toiles", "categorie": "-", "nom_epci": "CA Saint-Brieuc Armor Agglom\u00e9ration", "date_de_publication_de_l_etablissement": "2013-01-23", "nom_reg": "BRETAGNE", "courriel": "bonsaintnicolas@yahoo.fr", "adresse": "8 place de l'\u00e9glise", "nom_commercial": "AU BON SAINT NICOLAS", "date_de_classement": "2013-01-23", "telephone": "0296322103", "capacite_daccueil_personnes": 20, "typologie_etablissement": "H\u00d4TEL", "nombre_de_chambres": 14, "code_postal": "22120", "nom_dep": "COTES-D'ARMOR", "coordonnees": [48.514093, -2.66824], "site_internet": "-"}, "geometry": {"type": "Point", "coordinates": [-2.66824, 48.514093]}, "record_timestamp": "2020-07-08T10:30:41.649+02:00"},{"datasetid": "hebergements-classes", "recordid": "ca2771b8d8e73d55499b211623ecc15444525666", "fields": {"commune": "PERROS-GUIREC", "classement": "4 \u00e9toiles", "categorie": "-", "nom_epci": "CA Lannion-Tr\u00e9gor Communaut\u00e9", "date_de_publication_de_l_etablissement": "2016-08-04", "nom_reg": "BRETAGNE", "courriel": "infos@castelbeausite.com", "adresse": "PLAGE DE SAINT GUIREC PLOUMANAC'H", "nom_commercial": "H\u00d4TEL CASTEL BEAU SITE", "date_de_classement": "2016-08-04", "telephone": "0296914087", "capacite_daccueil_personnes": 69, "typologie_etablissement": "H\u00d4TEL", "nombre_de_chambres": 32, "code_postal": "22700", "nom_dep": "COTES-D'ARMOR", "coordonnees": [48.825969, -3.481344], "site_internet": "http://www.castelbeausite.com"}, "geometry": {"type": "Point", "coordinates": [-3.481344, 48.825969]}, "record_timestamp": "2020-07-08T10:30:41.649+02:00"},{"datasetid": "hebergements-classes", "recordid": "5e792043ac997a4acf1199635915c9c6825c9848", "fields": {"commune": "BINIC", "classement": "3 \u00e9toiles", "categorie": "-", "nom_epci": "CA Saint-Brieuc Armor Agglom\u00e9ration", "date_de_publication_de_l_etablissement": "2013-04-11", "nom_reg": "BRETAGNE", "courriel": "reservations@vacanciel.com", "adresse": "Avenue de Bernains", "nom_commercial": "H\u00d4TEL DE LA PLAGE", "date_de_classement": "2013-04-11", "telephone": "0475824545", "capacite_daccueil_personnes": 90, "typologie_etablissement": "H\u00d4TEL", "nombre_de_chambres": 39, "code_postal": "22520", "nom_dep": "COTES-D'ARMOR", "coordonnees": [48.595897, -2.823391], "site_internet": "www.vacanciel.com"}, "geometry": {"type": "Point", "coordinates": [-2.823391, 48.595897]}, "record_timestamp": "2020-07-08T10:30:41.649+02:00"},{"datasetid": "hebergements-classes", "recordid": "2399a0dd84528f23eb30ed13e49d05460324a992", "fields": {"commune": "TR\u00c9GUEUX", "classement": "2 \u00e9toiles", "categorie": "-", "nom_epci": "CA Saint-Brieuc Armor Agglom\u00e9ration", "date_de_publication_de_l_etablissement": "2014-03-02", "nom_reg": "BRETAGNE", "courriel": "bb_4145@hotelbb.com", "adresse": "Rue Alain Colas, La Hazaie", "nom_commercial": "H\u00d4TEL B&B SAINT-BRIEUC", "date_de_classement": "2014-03-02", "telephone": "0892788093", "capacite_daccueil_personnes": 144, "typologie_etablissement": "H\u00d4TEL", "nombre_de_chambres": 60, "code_postal": "22950", "nom_dep": "COTES-D'ARMOR", "coordonnees": [48.491056, -2.721076], "site_internet": "www.hotelbb.com"}, "geometry": {"type": "Point", "coordinates": [-2.721076, 48.491056]}, "record_timestamp": "2020-07-08T10:30:41.649+02:00"},{"datasetid": "hebergements-classes", "recordid": "1d98d97ad40995130fe5b224c05562540ae530fc", "fields": {"commune": "SAINT-CAST-LE-GUILDO", "classement": "2 \u00e9toiles", "categorie": "-", "nom_epci": "CA Dinan Agglom\u00e9ration", "date_de_publication_de_l_etablissement": "2017-02-21", "nom_reg": "BRETAGNE", "courriel": "port.jacquet@wanadoo.fr", "adresse": "32 Rue du Port", "nom_commercial": "H\u00d4TEL PORT JACQUET", "date_de_classement": "2017-02-21", "telephone": "0296419718", "capacite_daccueil_personnes": 49, "typologie_etablissement": "H\u00d4TEL", "nombre_de_chambres": 20, "code_postal": "22380", "nom_dep": "COTES-D'ARMOR", "coordonnees": [48.638775, -2.253269], "site_internet": "http://www.port-jacquet.com"}, "geometry": {"type": "Point", "coordinates": [-2.253269, 48.638775]}, "record_timestamp": "2020-07-08T10:30:41.649+02:00"},{"datasetid": "hebergements-classes", "recordid": "c60998a2cd47044741a197f52ac811375d83a962", "fields": {"commune": "LANNION", "classement": "3 \u00e9toiles", "categorie": "-", "nom_epci": "CA Lannion-Tr\u00e9gor Communaut\u00e9", "date_de_publication_de_l_etablissement": "2016-11-11", "nom_reg": "BRETAGNE", "courriel": "laetitia.kyriad.lannion@orange.fr", "adresse": "CHEMIN DE KERZOLLES", "nom_commercial": "H\u00d4TEL KYRIAD LANNION", "date_de_classement": "2016-11-11", "telephone": "0296487018", "capacite_daccueil_personnes": 95, "typologie_etablissement": "H\u00d4TEL", "nombre_de_chambres": 47, "code_postal": "22300", "nom_dep": "COTES-D'ARMOR", "coordonnees": [48.749961, -3.45897], "site_internet": "http://www.kyriad-lannion.fr"}, "geometry": {"type": "Point", "coordinates": [-3.45897, 48.749961]}, "record_timestamp": "2020-07-08T10:30:41.649+02:00"}]