[{"datasetid": "hebergements-classes", "recordid": "9b9b43a630e760c6d90d74438dd9620292fde19a", "fields": {"commune": "MONTAUBAN", "classement": "3 \u00e9toiles", "categorie": "-", "nom_epci": "CA Grand Montauban", "date_de_publication_de_l_etablissement": "2016-12-11", "nom_reg": "OCCITANIE", "courriel": "h1769-gm@accor.com", "adresse": "50 ROUTE DE SAINT-MARTIAL", "nom_commercial": "H\u00d4TEL IBIS MONTAUBAN", "date_de_classement": "2016-12-11", "telephone": "0563202088", "capacite_daccueil_personnes": 133, "typologie_etablissement": "H\u00d4TEL", "nombre_de_chambres": 62, "code_postal": "82000", "nom_dep": "TARN-ET-GARONNE", "coordonnees": [44.00558, 1.383129], "site_internet": "http://www.accorhotels.com/fr/hotel-1769-ibis-montauban/index.shtml"}, "geometry": {"type": "Point", "coordinates": [1.383129, 44.00558]}, "record_timestamp": "2020-07-08T10:30:41.649+02:00"},{"datasetid": "hebergements-classes", "recordid": "d803e0c954ab08d7c32b981a450b45cee6d02a85", "fields": {"commune": "BIOULE", "classement": "3 \u00e9toiles", "categorie": "-", "nom_epci": "CC Quercy Vert-Aveyron", "date_de_publication_de_l_etablissement": "2017-08-28", "nom_reg": "OCCITANIE", "courriel": "contact.lesboissieres@orange.fr", "adresse": "708 route de caussade", "nom_commercial": "H\u00d4TEL LES BOISSI\u00c8RES", "date_de_classement": "2017-08-28", "telephone": "0563245002", "capacite_daccueil_personnes": 18, "typologie_etablissement": "H\u00d4TEL", "nombre_de_chambres": 8, "code_postal": "82800", "nom_dep": "TARN-ET-GARONNE", "coordonnees": [44.093635, 1.533786], "site_internet": "http://www.lesboissieres.com/"}, "geometry": {"type": "Point", "coordinates": [1.533786, 44.093635]}, "record_timestamp": "2020-07-08T10:30:41.649+02:00"},{"datasetid": "hebergements-classes", "recordid": "9a95754e0ea23a8a21092fec6563f904b81b8601", "fields": {"commune": "CASTELSARRASIN", "classement": "2 \u00e9toiles", "categorie": "-", "nom_epci": "CC Terres des Confluences", "date_de_publication_de_l_etablissement": "2012-11-23", "nom_reg": "OCCITANIE", "courriel": "mavrick2@orange.fr", "adresse": "385 chemin de caussade bas", "nom_commercial": "H\u00d4TEL RESTAURANT FELIX", "date_de_classement": "2012-11-23", "telephone": "0563321497", "capacite_daccueil_personnes": 30, "typologie_etablissement": "H\u00d4TEL", "nombre_de_chambres": 14, "code_postal": "82100", "nom_dep": "TARN-ET-GARONNE", "coordonnees": [44.076728, 1.097467], "site_internet": "www.restaurant-felix.com"}, "geometry": {"type": "Point", "coordinates": [1.097467, 44.076728]}, "record_timestamp": "2020-07-08T10:30:41.649+02:00"},{"datasetid": "hebergements-classes", "recordid": "cef6a8241a6df23618fede7ea8425366935e40ec", "fields": {"commune": "MONTAUBAN", "classement": "4 \u00e9toiles", "categorie": "-", "nom_epci": "CA Grand Montauban", "date_de_publication_de_l_etablissement": "2017-05-07", "nom_reg": "OCCITANIE", "courriel": "contact@capucins.fr", "adresse": "6/8 quai de Verdun", "nom_commercial": "ABBAYE DES CAPUCINS", "date_de_classement": "2017-05-07", "telephone": "0563220000", "capacite_daccueil_personnes": 203, "typologie_etablissement": "H\u00d4TEL", "nombre_de_chambres": 85, "code_postal": "82000", "nom_dep": "TARN-ET-GARONNE", "coordonnees": [44.020595, 1.349551], "site_internet": "http://abbayedescapucins.fr"}, "geometry": {"type": "Point", "coordinates": [1.349551, 44.020595]}, "record_timestamp": "2020-07-08T10:30:41.649+02:00"},{"datasetid": "hebergements-classes", "recordid": "00e4240eed2acc8a34a0cc6932ca92b4d778ffa2", "fields": {"commune": "VALENCE", "classement": "2 \u00e9toiles", "categorie": "-", "nom_epci": "CC des Deux Rives", "date_de_publication_de_l_etablissement": "2017-04-18", "nom_reg": "OCCITANIE", "courriel": "letoutvabien935@orange.fr", "adresse": "30 place Sylvain Dumon", "nom_commercial": "H\u00d4TEL LE TOUT VA BIEN", "date_de_classement": "2017-04-18", "telephone": "05 63 39 09 26", "capacite_daccueil_personnes": 42, "typologie_etablissement": "H\u00d4TEL", "nombre_de_chambres": 21, "code_postal": "82400", "nom_dep": "TARN-ET-GARONNE", "coordonnees": [44.10743, 0.888763], "site_internet": "http://www.hotel-letoutvabien.fr"}, "geometry": {"type": "Point", "coordinates": [0.888763, 44.10743]}, "record_timestamp": "2020-07-08T10:30:41.649+02:00"},{"datasetid": "hebergements-classes", "recordid": "39fb6f8a1a1480012ef9899e8c7f8ce4fc9eacb7", "fields": {"commune": "LAMAGIST\u00c8RE", "classement": "2 \u00e9toiles", "categorie": "-", "nom_epci": "CC des Deux Rives", "date_de_publication_de_l_etablissement": "2012-11-22", "nom_reg": "OCCITANIE", "courriel": "contact@auberge-lamagitere.com", "adresse": "34 route de la gare", "nom_commercial": "AUBERGE DE LAMAGIST\u00c8RE", "date_de_classement": "2012-11-22", "telephone": "0563296820", "capacite_daccueil_personnes": 55, "typologie_etablissement": "H\u00d4TEL", "nombre_de_chambres": 25, "code_postal": "82360", "nom_dep": "TARN-ET-GARONNE", "coordonnees": [44.126106, 0.824737], "site_internet": "www.auberge-lamagistere.com"}, "geometry": {"type": "Point", "coordinates": [0.824737, 44.126106]}, "record_timestamp": "2020-07-08T10:30:41.649+02:00"},{"datasetid": "hebergements-classes", "recordid": "4b7b6e2207287e1f52b2ba18978ab2925363b580", "fields": {"commune": "GRISOLLES", "classement": "2 \u00e9toiles", "categorie": "-", "nom_epci": "CC Grand Sud Tarn et Garonne", "date_de_publication_de_l_etablissement": "2013-01-15", "nom_reg": "OCCITANIE", "courriel": "relaisdesgarrigues@orange.fr", "adresse": "130 route de fronton", "nom_commercial": "H\u00d4TEL RESTAURANT LE RELAIS DES GARRIGUES", "date_de_classement": "2013-01-15", "telephone": "0563673159", "capacite_daccueil_personnes": 85, "typologie_etablissement": "H\u00d4TEL", "nombre_de_chambres": 33, "code_postal": "82170", "nom_dep": "TARN-ET-GARONNE", "coordonnees": [43.829267, 1.303209], "site_internet": "-"}, "geometry": {"type": "Point", "coordinates": [1.303209, 43.829267]}, "record_timestamp": "2020-07-08T10:30:41.649+02:00"},{"datasetid": "hebergements-classes", "recordid": "89ffbb8947f645b5725ff2c8a2cda76c1d09f81f", "fields": {"commune": "CASTELSARRASIN", "classement": "2 \u00e9toiles", "categorie": "-", "nom_epci": "CC Terres des Confluences", "date_de_publication_de_l_etablissement": "2017-01-02", "nom_reg": "OCCITANIE", "courriel": "absolu0328@orange.fr", "adresse": "11 promenade du ch\u00e2teau", "nom_commercial": "H\u00d4TEL ABSOLU", "date_de_classement": "2017-01-02", "telephone": "0563953323", "capacite_daccueil_personnes": 12, "typologie_etablissement": "H\u00d4TEL", "nombre_de_chambres": 6, "code_postal": "82100", "nom_dep": "TARN-ET-GARONNE", "coordonnees": [44.037641, 1.106039], "site_internet": "http://hotelabsolu.fr/FR/"}, "geometry": {"type": "Point", "coordinates": [1.106039, 44.037641]}, "record_timestamp": "2020-07-08T10:30:41.649+02:00"},{"datasetid": "hebergements-classes", "recordid": "be3caa2d4bd24eb758f79bc097306bc91e5b7ecd", "fields": {"commune": "MONTAUBAN", "classement": "3 \u00e9toiles", "categorie": "-", "nom_epci": "CA Grand Montauban", "date_de_publication_de_l_etablissement": "2017-01-02", "nom_reg": "OCCITANIE", "courriel": "info@hotel-commerce-montauban.com", "adresse": "9 Place Franklin Roosevelt", "nom_commercial": "GEORGE H\u00d4TEL", "date_de_classement": "2017-01-02", "telephone": "0563663132", "capacite_daccueil_personnes": 60, "typologie_etablissement": "H\u00d4TEL", "nombre_de_chambres": 27, "code_postal": "82000", "nom_dep": "TARN-ET-GARONNE", "coordonnees": [44.015417, 1.354042], "site_internet": "http://www.hotel-commerce-montauban.com"}, "geometry": {"type": "Point", "coordinates": [1.354042, 44.015417]}, "record_timestamp": "2020-07-08T10:30:41.649+02:00"},{"datasetid": "hebergements-classes", "recordid": "bc924416dd5c1ff09d06078a708d36afe829027e", "fields": {"commune": "MONTAIGU-DE-QUERCY", "classement": "2 \u00e9toiles", "categorie": "-", "nom_epci": "CC du Pays de Serres en Quercy", "date_de_publication_de_l_etablissement": "2016-06-17", "nom_reg": "OCCITANIE", "courriel": "lemidihotel82@gmail.com", "adresse": "41 rue albert caillau", "nom_commercial": "H\u00d4TEL LE MIDI", "date_de_classement": "2016-06-17", "telephone": "0563324653", "capacite_daccueil_personnes": 14, "typologie_etablissement": "H\u00d4TEL", "nombre_de_chambres": 7, "code_postal": "82150", "nom_dep": "TARN-ET-GARONNE", "coordonnees": [44.339855, 1.017798], "site_internet": "http://hotelrestaurantlemidi.fr/"}, "geometry": {"type": "Point", "coordinates": [1.017798, 44.339855]}, "record_timestamp": "2020-07-08T10:30:41.649+02:00"},{"datasetid": "hebergements-classes", "recordid": "4928ee9f6d291619ba34871aed37d5ef8978aed9", "fields": {"commune": "MONTAUBAN", "classement": "3 \u00e9toiles", "categorie": "-", "nom_epci": "CA Grand Montauban", "date_de_publication_de_l_etablissement": "2017-04-18", "nom_reg": "OCCITANIE", "courriel": "contact@kyriadmontauban.fr", "adresse": "1461 ROUTE DU NORD", "nom_commercial": "H\u00d4TEL KYRIAD MONTAUBAN", "date_de_classement": "2017-04-18", "telephone": "0563665161", "capacite_daccueil_personnes": 83, "typologie_etablissement": "H\u00d4TEL", "nombre_de_chambres": 38, "code_postal": "82000", "nom_dep": "TARN-ET-GARONNE", "coordonnees": [44.047212, 1.392779], "site_internet": "http://www.kyriad-montauban.fr/"}, "geometry": {"type": "Point", "coordinates": [1.392779, 44.047212]}, "record_timestamp": "2020-07-08T10:30:41.649+02:00"},{"datasetid": "hebergements-classes", "recordid": "da1b13a07236625dd36be125f1e49fedb376e87f", "fields": {"commune": "MOISSAC", "classement": "2 \u00e9toiles", "categorie": "-", "nom_epci": "CC Terres des Confluences", "date_de_publication_de_l_etablissement": "2017-07-06", "nom_reg": "OCCITANIE", "courriel": "hotel@cretesdepignols.com", "adresse": "1167 C\u00f4te de Pignols", "nom_commercial": "H\u00d4TEL DES CR\u00caTES DE PIGNOLS", "date_de_classement": "2017-07-06", "telephone": "05 63 04 04 04", "capacite_daccueil_personnes": 27, "typologie_etablissement": "H\u00d4TEL", "nombre_de_chambres": 12, "code_postal": "82200", "nom_dep": "TARN-ET-GARONNE", "coordonnees": [44.125832, 1.122478], "site_internet": "http://www.cretesdepignols.com/"}, "geometry": {"type": "Point", "coordinates": [1.122478, 44.125832]}, "record_timestamp": "2020-07-08T10:30:41.649+02:00"},{"datasetid": "hebergements-classes", "recordid": "43e5c5efa147e13eb628116e9ce4498d42078fa7", "fields": {"commune": "MOISSAC", "classement": "3 \u00e9toiles", "categorie": "-", "nom_epci": "CC Terres des Confluences", "date_de_publication_de_l_etablissement": "2017-03-15", "nom_reg": "OCCITANIE", "courriel": "hotelarmateur@orange.fr", "adresse": "22 rue du pont", "nom_commercial": "H\u00d4TEL L'ARMATEUR", "date_de_classement": "2017-03-15", "telephone": "0563328510", "capacite_daccueil_personnes": 34, "typologie_etablissement": "H\u00d4TEL", "nombre_de_chambres": 16, "code_postal": "82200", "nom_dep": "TARN-ET-GARONNE", "coordonnees": [44.100929, 1.08251], "site_internet": "http://hotelarmateur.fr"}, "geometry": {"type": "Point", "coordinates": [1.08251, 44.100929]}, "record_timestamp": "2020-07-08T10:30:41.649+02:00"},{"datasetid": "hebergements-classes", "recordid": "5883051526be0b7b8fbe51cb2c81c2cb6084381a", "fields": {"commune": "MONTAUBAN", "classement": "2 \u00e9toiles", "categorie": "-", "nom_epci": "CA Grand Montauban", "date_de_publication_de_l_etablissement": "2016-12-11", "nom_reg": "OCCITANIE", "courriel": "h7950@accor.com", "adresse": "50 Route de Saint-Martial", "nom_commercial": "H\u00d4TEL IBIS BUDGET MONTAUBAN LES CHAUMES", "date_de_classement": "2016-12-11", "telephone": "0892701284", "capacite_daccueil_personnes": 105, "typologie_etablissement": "H\u00d4TEL", "nombre_de_chambres": 41, "code_postal": "82000", "nom_dep": "TARN-ET-GARONNE", "coordonnees": [44.00558, 1.383129], "site_internet": "http://www.accorhotels.com/fr/hotel-7950-ibis-budget-montauban-les-chaumes/index.shtml"}, "geometry": {"type": "Point", "coordinates": [1.383129, 44.00558]}, "record_timestamp": "2020-07-08T10:30:41.649+02:00"},{"datasetid": "hebergements-classes", "recordid": "5a2f1f63ec0785a223790fbb933a947f9a00e9e2", "fields": {"commune": "BEAUMONT-DE-LOMAGNE", "classement": "2 \u00e9toiles", "categorie": "-", "nom_epci": "CC de la Lomagne Tarn-et-Garonnaise", "date_de_publication_de_l_etablissement": "2017-04-26", "nom_reg": "OCCITANIE", "courriel": "hotelrestaurantlesaintjean@gmail.com", "adresse": "58 rue Mar\u00e9chal Foch", "nom_commercial": "H\u00d4TEL RESTAURANT LE SAINT JEAN", "date_de_classement": "2017-04-26", "telephone": "0563023102", "capacite_daccueil_personnes": 32, "typologie_etablissement": "H\u00d4TEL", "nombre_de_chambres": 14, "code_postal": "82500", "nom_dep": "TARN-ET-GARONNE", "coordonnees": [43.883303, 0.991587], "site_internet": "http://www.hotelrestaurantlesaintjean.fr/"}, "geometry": {"type": "Point", "coordinates": [0.991587, 43.883303]}, "record_timestamp": "2020-07-08T10:30:41.649+02:00"},{"datasetid": "hebergements-classes", "recordid": "f497c90804a5d8c4ee143f8525c91b6f68ca8709", "fields": {"commune": "N\u00c8GREPELISSE", "classement": "3 \u00e9toiles", "categorie": "-", "nom_epci": "CC Quercy Vert-Aveyron", "date_de_publication_de_l_etablissement": "2013-11-04", "nom_reg": "OCCITANIE", "courriel": "auxgourmandisesquercynoises@yahoo.fr", "adresse": "60 route de Montricoux", "nom_commercial": "H\u00d4TEL DES ARTS", "date_de_classement": "2013-11-04", "telephone": "0563642341", "capacite_daccueil_personnes": 44, "typologie_etablissement": "H\u00d4TEL", "nombre_de_chambres": 22, "code_postal": "82800", "nom_dep": "TARN-ET-GARONNE", "coordonnees": [44.072595, 1.536752], "site_internet": "http://www.hotel-des-arts.eu/"}, "geometry": {"type": "Point", "coordinates": [1.536752, 44.072595]}, "record_timestamp": "2020-07-08T10:30:41.649+02:00"},{"datasetid": "hebergements-classes", "recordid": "0b7e0622823d5d054c2ad4ed9ba285ff8b92e4d3", "fields": {"commune": "MONTAUBAN", "classement": "2 \u00e9toiles", "categorie": "-", "nom_epci": "CA Grand Montauban", "date_de_publication_de_l_etablissement": "2013-01-08", "nom_reg": "OCCITANIE", "courriel": "montauban@deltourhotel.com", "adresse": "16 Impasse DAGUERRE", "nom_commercial": "DELTOUR HOTEL", "date_de_classement": "2013-01-08", "telephone": "05.63.67.68.69", "capacite_daccueil_personnes": 93, "typologie_etablissement": "H\u00d4TEL", "nombre_de_chambres": 38, "code_postal": "82000", "nom_dep": "TARN-ET-GARONNE", "coordonnees": [43.981161, 1.330589], "site_internet": "www.deltourhotel.com"}, "geometry": {"type": "Point", "coordinates": [1.330589, 43.981161]}, "record_timestamp": "2020-07-08T10:30:41.649+02:00"},{"datasetid": "hebergements-classes", "recordid": "55ed1e5f37ec33e303cef560ca0bfff204290bab", "fields": {"commune": "CASTELSARRASIN", "classement": "2 \u00e9toiles", "categorie": "-", "nom_epci": "CC Terres des Confluences", "date_de_publication_de_l_etablissement": "2017-09-07", "nom_reg": "OCCITANIE", "courriel": "info@hotelmarceillac.com", "adresse": "54 RUE DE L\u2019\u00c9GALIT\u00c9", "nom_commercial": "H\u00d4TEL MARCEILLAC", "date_de_classement": "2017-09-07", "telephone": "0563323010", "capacite_daccueil_personnes": 26, "typologie_etablissement": "H\u00d4TEL", "nombre_de_chambres": 12, "code_postal": "82100", "nom_dep": "TARN-ET-GARONNE", "coordonnees": [44.03916, 1.108261], "site_internet": "www.hotelmarceillac.com"}, "geometry": {"type": "Point", "coordinates": [1.108261, 44.03916]}, "record_timestamp": "2020-07-08T10:30:41.649+02:00"},{"datasetid": "hebergements-classes", "recordid": "a1c9bbb9ef10d6a1f000c4205ad552996716d45a", "fields": {"commune": "MONTAUBAN", "classement": "4 \u00e9toiles", "categorie": "-", "nom_epci": "CA Grand Montauban", "date_de_publication_de_l_etablissement": "2016-03-30", "nom_reg": "OCCITANIE", "courriel": "H2183@accor.com", "adresse": "12 rue Notre Dame", "nom_commercial": "H\u00d4TEL MERCURE MONTAUBAN", "date_de_classement": "2016-03-30", "telephone": "0563631723", "capacite_daccueil_personnes": 90, "typologie_etablissement": "H\u00d4TEL", "nombre_de_chambres": 44, "code_postal": "82000", "nom_dep": "TARN-ET-GARONNE", "coordonnees": [44.015707, 1.355173], "site_internet": "http://www.accorhotels.com/fr/hotel-2183-hotel-mercure-montauban/index.shtml"}, "geometry": {"type": "Point", "coordinates": [1.355173, 44.015707]}, "record_timestamp": "2020-07-08T10:30:41.649+02:00"},{"datasetid": "hebergements-classes", "recordid": "796b82e61deb403fd3f1e75977deabe47cd89f4f", "fields": {"commune": "MOISSAC", "classement": "3 \u00e9toiles", "categorie": "-", "nom_epci": "CC Terres des Confluences", "date_de_publication_de_l_etablissement": "2012-10-16", "nom_reg": "OCCITANIE", "courriel": "hotel@lemoulindemoissac.com", "adresse": "1 promenade Sancert", "nom_commercial": "H\u00d4TEL RESTAURANT SPA LE MOULIN DE MOISSAC", "date_de_classement": "2012-10-16", "telephone": "0563328888", "capacite_daccueil_personnes": 431, "typologie_etablissement": "H\u00d4TEL", "nombre_de_chambres": 36, "code_postal": "82200", "nom_dep": "TARN-ET-GARONNE", "coordonnees": [44.100097, 1.086057], "site_internet": "www.lemoulindemoissac.com"}, "geometry": {"type": "Point", "coordinates": [1.086057, 44.100097]}, "record_timestamp": "2020-07-08T10:30:41.649+02:00"},{"datasetid": "hebergements-classes", "recordid": "79509713eaa9ef8cf44975681a6334550c5af47b", "fields": {"commune": "VA\u00cfSSAC", "classement": "2 \u00e9toiles", "categorie": "-", "nom_epci": "CC Quercy Vert-Aveyron", "date_de_publication_de_l_etablissement": "2017-07-24", "nom_reg": "OCCITANIE", "courriel": "chez-terrassier@wanadoo.fr", "adresse": "205 rue du village", "nom_commercial": "H\u00d4TEL CHEZ TERRASSIER", "date_de_classement": "2017-07-24", "telephone": "0563309460", "capacite_daccueil_personnes": 36, "typologie_etablissement": "H\u00d4TEL", "nombre_de_chambres": 18, "code_postal": "82800", "nom_dep": "TARN-ET-GARONNE", "coordonnees": [44.033205, 1.569215], "site_internet": "http://www.chezterrassier.com/"}, "geometry": {"type": "Point", "coordinates": [1.569215, 44.033205]}, "record_timestamp": "2020-07-08T10:30:41.649+02:00"},{"datasetid": "hebergements-classes", "recordid": "981ff94df484ce9cf8b9032bf7b7ca2a3f08ca71", "fields": {"commune": "BEAUMONT-DE-LOMAGNE", "classement": "3 \u00e9toiles", "categorie": "-", "nom_epci": "CC de la Lomagne Tarn-et-Garonnaise", "date_de_publication_de_l_etablissement": "2014-09-18", "nom_reg": "OCCITANIE", "courriel": "info@maisondeslumieres.com", "adresse": "38 rue de la font", "nom_commercial": "H\u00d4TEL LA MAISON DES LUMI\u00c8RES", "date_de_classement": "2014-09-18", "telephone": "0581981520", "capacite_daccueil_personnes": 15, "typologie_etablissement": "H\u00d4TEL", "nombre_de_chambres": 6, "code_postal": "82500", "nom_dep": "TARN-ET-GARONNE", "coordonnees": [43.881186, 0.988718], "site_internet": "www.maisondeslumieres.com"}, "geometry": {"type": "Point", "coordinates": [0.988718, 43.881186]}, "record_timestamp": "2020-07-08T10:30:41.649+02:00"},{"datasetid": "hebergements-classes", "recordid": "996a0c48303351c1b847d6c2472787cf82ff67c3", "fields": {"commune": "MONTAUBAN", "classement": "2 \u00e9toiles", "categorie": "-", "nom_epci": "CA Grand Montauban", "date_de_publication_de_l_etablissement": "2015-01-14", "nom_reg": "OCCITANIE", "courriel": "bb_4506@hotelbb.com", "adresse": "600 route du nord, Futuropole", "nom_commercial": "H\u00d4TEL B&B MONTAUBAN", "date_de_classement": "2015-01-14", "telephone": "0563216701", "capacite_daccueil_personnes": 172, "typologie_etablissement": "H\u00d4TEL", "nombre_de_chambres": 72, "code_postal": "82000", "nom_dep": "TARN-ET-GARONNE", "coordonnees": [44.039726, 1.385694], "site_internet": "http://www.hotel-bb.com/fr/home.htm"}, "geometry": {"type": "Point", "coordinates": [1.385694, 44.039726]}, "record_timestamp": "2020-07-08T10:30:41.649+02:00"},{"datasetid": "hebergements-classes", "recordid": "086fbee87720ef3649f90358d0320ae860afc7b3", "fields": {"commune": "CAUSSADE", "classement": "2 \u00e9toiles", "categorie": "-", "nom_epci": "CC du Quercy Caussadais", "date_de_publication_de_l_etablissement": "2017-09-15", "nom_reg": "OCCITANIE", "courriel": "contact-hotel@hotellarroque.fr", "adresse": "18 avenue du 8 Mai 1945", "nom_commercial": "H\u00d4TEL R\u00c9SIDENCE LARROQUE", "date_de_classement": "2017-09-15", "telephone": "05 63 65 11 77", "capacite_daccueil_personnes": 48, "typologie_etablissement": "H\u00d4TEL", "nombre_de_chambres": 18, "code_postal": "82300", "nom_dep": "TARN-ET-GARONNE", "coordonnees": [44.162058, 1.534322], "site_internet": "www.hotellarroque.fr"}, "geometry": {"type": "Point", "coordinates": [1.534322, 44.162058]}, "record_timestamp": "2020-07-08T10:30:41.649+02:00"},{"datasetid": "hebergements-classes", "recordid": "468994d1da2971910aee41d5b73bb40b2bca9733", "fields": {"commune": "LAUZERTE", "classement": "3 \u00e9toiles", "categorie": "-", "nom_epci": "CC du Pays de Serres en Quercy", "date_de_publication_de_l_etablissement": "2017-07-18", "nom_reg": "OCCITANIE", "courriel": "hotel@lebelvedere.biz", "adresse": "Montagudet", "nom_commercial": "H\u00d4TEL LE BELV\u00c9D\u00c8RE", "date_de_classement": "2017-07-18", "telephone": "0563955110", "capacite_daccueil_personnes": 57, "typologie_etablissement": "H\u00d4TEL", "nombre_de_chambres": 22, "code_postal": "82110", "nom_dep": "TARN-ET-GARONNE", "coordonnees": [44.243218, 1.090317], "site_internet": "www.lebelvedere.biz"}, "geometry": {"type": "Point", "coordinates": [1.090317, 44.243218]}, "record_timestamp": "2020-07-08T10:30:41.649+02:00"},{"datasetid": "hebergements-classes", "recordid": "cf6b14d7b164ce1abe4f91e0442aa979f77df001", "fields": {"commune": "CAUSSADE", "classement": "2 \u00e9toiles", "categorie": "-", "nom_epci": "CC du Quercy Caussadais", "date_de_publication_de_l_etablissement": "2013-01-16", "nom_reg": "OCCITANIE", "courriel": "hotel-resto-dupont@cegetel.net", "adresse": "25 rue des r\u00e9collets", "nom_commercial": "H\u00d4TEL RESTAURANT DUPONT", "date_de_classement": "2013-01-16", "telephone": "0563650500", "capacite_daccueil_personnes": 61, "typologie_etablissement": "H\u00d4TEL", "nombre_de_chambres": 30, "code_postal": "82300", "nom_dep": "TARN-ET-GARONNE", "coordonnees": [44.162993, 1.538076], "site_internet": "www.hotel-restaurant-dupont.com"}, "geometry": {"type": "Point", "coordinates": [1.538076, 44.162993]}, "record_timestamp": "2020-07-08T10:30:41.649+02:00"},{"datasetid": "hebergements-classes", "recordid": "5121acd4c84f1cdb9f85ea7776af73e64f20a2e3", "fields": {"commune": "MONCLAR-DE-QUERCY", "classement": "2 \u00e9toiles", "categorie": "-", "nom_epci": "CC Quercy Vert-Aveyron", "date_de_publication_de_l_etablissement": "2017-07-18", "nom_reg": "OCCITANIE", "courriel": "philippelefrancois@yahoo.com", "adresse": "12 AVENUE DU LAC", "nom_commercial": "L'HOSTELLERIE DES LACS", "date_de_classement": "2017-07-18", "telephone": "0563264264", "capacite_daccueil_personnes": 20, "typologie_etablissement": "H\u00d4TEL", "nombre_de_chambres": 6, "code_postal": "82230", "nom_dep": "TARN-ET-GARONNE", "coordonnees": [43.966395, 1.586462], "site_internet": "http://www.lhostelleriedeslacs.fr"}, "geometry": {"type": "Point", "coordinates": [1.586462, 43.966395]}, "record_timestamp": "2020-07-08T10:30:41.649+02:00"}]